{"nodes": [{"id": "c_users_keanghour_documents_github_fnode_fnode_supportproject_sing_box_experimental_libbox_tun_go", "label": "tun.go", "file_type": "code", "source_file": "C:\\Users\\Keanghour\\Documents\\GitHub\\FNode\\FNode\\SupportProject\\sing-box\\experimental\\libbox\\tun.go", "source_location": "L1"}, {"id": "libbox_tunoptions", "label": "TunOptions", "file_type": "code", "source_file": "C:\\Users\\Keanghour\\Documents\\GitHub\\FNode\\FNode\\SupportProject\\sing-box\\experimental\\libbox\\tun.go", "source_location": "L13"}, {"id": "libbox_routeprefix", "label": "RoutePrefix", "file_type": "code", "source_file": "C:\\Users\\Keanghour\\Documents\\GitHub\\FNode\\FNode\\SupportProject\\sing-box\\experimental\\libbox\\tun.go", "source_location": "L35"}, {"id": "libbox_routeprefix_address", "label": ".Address()", "file_type": "code", "source_file": "C:\\Users\\Keanghour\\Documents\\GitHub\\FNode\\FNode\\SupportProject\\sing-box\\experimental\\libbox\\tun.go", "source_location": "L40"}, {"id": "libbox_routeprefix_prefix", "label": ".Prefix()", "file_type": "code", "source_file": "C:\\Users\\Keanghour\\Documents\\GitHub\\FNode\\FNode\\SupportProject\\sing-box\\experimental\\libbox\\tun.go", "source_location": "L44"}, {"id": "libbox_routeprefix_mask", "label": ".Mask()", "file_type": "code", "source_file": "C:\\Users\\Keanghour\\Documents\\GitHub\\FNode\\FNode\\SupportProject\\sing-box\\experimental\\libbox\\tun.go", "source_location": "L48"}, {"id": "libbox_routeprefix_string", "label": ".String()", "file_type": "code", "source_file": "C:\\Users\\Keanghour\\Documents\\GitHub\\FNode\\FNode\\SupportProject\\sing-box\\experimental\\libbox\\tun.go", "source_location": "L58"}, {"id": "libbox_routeprefixiterator", "label": "RoutePrefixIterator", "file_type": "code", "source_file": "C:\\Users\\Keanghour\\Documents\\GitHub\\FNode\\FNode\\SupportProject\\sing-box\\experimental\\libbox\\tun.go", "source_location": "L62"}, {"id": "libbox_tun_maprouteprefix", "label": "mapRoutePrefix()", "file_type": "code", "source_file": "C:\\Users\\Keanghour\\Documents\\GitHub\\FNode\\FNode\\SupportProject\\sing-box\\experimental\\libbox\\tun.go", "source_location": "L67"}, {"id": "libbox_tunoptions_getinet4address", "label": ".GetInet4Address()", "file_type": "code", "source_file": "C:\\Users\\Keanghour\\Documents\\GitHub\\FNode\\FNode\\SupportProject\\sing-box\\experimental\\libbox\\tun.go", "source_location": "L84"}, {"id": "libbox_tunoptions_getinet6address", "label": ".GetInet6Address()", "file_type": "code", "source_file": "C:\\Users\\Keanghour\\Documents\\GitHub\\FNode\\FNode\\SupportProject\\sing-box\\experimental\\libbox\\tun.go", "source_location": "L88"}, {"id": "libbox_tunoptions_getdnsserveraddress", "label": ".GetDNSServerAddress()", "file_type": "code", "source_file": "C:\\Users\\Keanghour\\Documents\\GitHub\\FNode\\FNode\\SupportProject\\sing-box\\experimental\\libbox\\tun.go", "source_location": "L92"}, {"id": "libbox_tunoptions_getmtu", "label": ".GetMTU()", "file_type": "code", "source_file": "C:\\Users\\Keanghour\\Documents\\GitHub\\FNode\\FNode\\SupportProject\\sing-box\\experimental\\libbox\\tun.go", "source_location": "L99"}, {"id": "libbox_tunoptions_getautoroute", "label": ".GetAutoRoute()", "file_type": "code", "source_file": "C:\\Users\\Keanghour\\Documents\\GitHub\\FNode\\FNode\\SupportProject\\sing-box\\experimental\\libbox\\tun.go", "source_location": "L103"}, {"id": "libbox_tunoptions_getstrictroute", "label": ".GetStrictRoute()", "file_type": "code", "source_file": "C:\\Users\\Keanghour\\Documents\\GitHub\\FNode\\FNode\\SupportProject\\sing-box\\experimental\\libbox\\tun.go", "source_location": "L107"}, {"id": "libbox_tunoptions_getinet4routeaddress", "label": ".GetInet4RouteAddress()", "file_type": "code", "source_file": "C:\\Users\\Keanghour\\Documents\\GitHub\\FNode\\FNode\\SupportProject\\sing-box\\experimental\\libbox\\tun.go", "source_location": "L111"}, {"id": "libbox_tunoptions_getinet6routeaddress", "label": ".GetInet6RouteAddress()", "file_type": "code", "source_file": "C:\\Users\\Keanghour\\Documents\\GitHub\\FNode\\FNode\\SupportProject\\sing-box\\experimental\\libbox\\tun.go", "source_location": "L115"}, {"id": "libbox_tunoptions_getinet4routeexcludeaddress", "label": ".GetInet4RouteExcludeAddress()", "file_type": "code", "source_file": "C:\\Users\\Keanghour\\Documents\\GitHub\\FNode\\FNode\\SupportProject\\sing-box\\experimental\\libbox\\tun.go", "source_location": "L119"}, {"id": "libbox_tunoptions_getinet6routeexcludeaddress", "label": ".GetInet6RouteExcludeAddress()", "file_type": "code", "source_file": "C:\\Users\\Keanghour\\Documents\\GitHub\\FNode\\FNode\\SupportProject\\sing-box\\experimental\\libbox\\tun.go", "source_location": "L123"}, {"id": "libbox_tunoptions_getinet4routerange", "label": ".GetInet4RouteRange()", "file_type": "code", "source_file": "C:\\Users\\Keanghour\\Documents\\GitHub\\FNode\\FNode\\SupportProject\\sing-box\\experimental\\libbox\\tun.go", "source_location": "L127"}, {"id": "libbox_tunoptions_getinet6routerange", "label": ".GetInet6RouteRange()", "file_type": "code", "source_file": "C:\\Users\\Keanghour\\Documents\\GitHub\\FNode\\FNode\\SupportProject\\sing-box\\experimental\\libbox\\tun.go", "source_location": "L133"}, {"id": "libbox_tunoptions_getincludepackage", "label": ".GetIncludePackage()", "file_type": "code", "source_file": "C:\\Users\\Keanghour\\Documents\\GitHub\\FNode\\FNode\\SupportProject\\sing-box\\experimental\\libbox\\tun.go", "source_location": "L139"}, {"id": "libbox_tunoptions_getexcludepackage", "label": ".GetExcludePackage()", "file_type": "code", "source_file": "C:\\Users\\Keanghour\\Documents\\GitHub\\FNode\\FNode\\SupportProject\\sing-box\\experimental\\libbox\\tun.go", "source_location": "L143"}, {"id": "libbox_tunoptions_ishttpproxyenabled", "label": ".IsHTTPProxyEnabled()", "file_type": "code", "source_file": "C:\\Users\\Keanghour\\Documents\\GitHub\\FNode\\FNode\\SupportProject\\sing-box\\experimental\\libbox\\tun.go", "source_location": "L147"}, {"id": "libbox_tunoptions_gethttpproxyserver", "label": ".GetHTTPProxyServer()", "file_type": "code", "source_file": "C:\\Users\\Keanghour\\Documents\\GitHub\\FNode\\FNode\\SupportProject\\sing-box\\experimental\\libbox\\tun.go", "source_location": "L154"}, {"id": "libbox_tunoptions_gethttpproxyserverport", "label": ".GetHTTPProxyServerPort()", "file_type": "code", "source_file": "C:\\Users\\Keanghour\\Documents\\GitHub\\FNode\\FNode\\SupportProject\\sing-box\\experimental\\libbox\\tun.go", "source_location": "L158"}, {"id": "libbox_tunoptions_gethttpproxybypassdomain", "label": ".GetHTTPProxyBypassDomain()", "file_type": "code", "source_file": "C:\\Users\\Keanghour\\Documents\\GitHub\\FNode\\FNode\\SupportProject\\sing-box\\experimental\\libbox\\tun.go", "source_location": "L162"}, {"id": "libbox_tunoptions_gethttpproxymatchdomain", "label": ".GetHTTPProxyMatchDomain()", "file_type": "code", "source_file": "C:\\Users\\Keanghour\\Documents\\GitHub\\FNode\\FNode\\SupportProject\\sing-box\\experimental\\libbox\\tun.go", "source_location": "L166"}], "edges": [{"source": "c_users_keanghour_documents_github_fnode_fnode_supportproject_sing_box_experimental_libbox_tun_go", "target": "go_pkg_net", "relation": "imports_from", "confidence": "EXTRACTED", "source_file": "C:\\Users\\Keanghour\\Documents\\GitHub\\FNode\\FNode\\SupportProject\\sing-box\\experimental\\libbox\\tun.go", "source_location": "L4", "weight": 1.0, "context": "import"}, {"source": "c_users_keanghour_documents_github_fnode_fnode_supportproject_sing_box_experimental_libbox_tun_go", "target": "go_pkg_net_netip", "relation": "imports_from", "confidence": "EXTRACTED", "source_file": "C:\\Users\\Keanghour\\Documents\\GitHub\\FNode\\FNode\\SupportProject\\sing-box\\experimental\\libbox\\tun.go", "source_location": "L5", "weight": 1.0, "context": "import"}, {"source": "c_users_keanghour_documents_github_fnode_fnode_supportproject_sing_box_experimental_libbox_tun_go", "target": "go_pkg_github_com_sagernet_sing_box_option", "relation": "imports_from", "confidence": "EXTRACTED", "source_file": "C:\\Users\\Keanghour\\Documents\\GitHub\\FNode\\FNode\\SupportProject\\sing-box\\experimental\\libbox\\tun.go", "source_location": "L7", "weight": 1.0, "context": "import"}, {"source": "c_users_keanghour_documents_github_fnode_fnode_supportproject_sing_box_experimental_libbox_tun_go", "target": "go_pkg_github_com_sagernet_sing_tun", "relation": "imports_from", "confidence": "EXTRACTED", "source_file": "C:\\Users\\Keanghour\\Documents\\GitHub\\FNode\\FNode\\SupportProject\\sing-box\\experimental\\libbox\\tun.go", "source_location": "L8", "weight": 1.0, "context": "import"}, {"source": "c_users_keanghour_documents_github_fnode_fnode_supportproject_sing_box_experimental_libbox_tun_go", "target": "go_pkg_github_com_sagernet_sing_common", "relation": "imports_from", "confidence": "EXTRACTED", "source_file": "C:\\Users\\Keanghour\\Documents\\GitHub\\FNode\\FNode\\SupportProject\\sing-box\\experimental\\libbox\\tun.go", "source_location": "L9", "weight": 1.0, "context": "import"}, {"source": "c_users_keanghour_documents_github_fnode_fnode_supportproject_sing_box_experimental_libbox_tun_go", "target": "go_pkg_github_com_sagernet_sing_common_exceptions", "relation": "imports_from", "confidence": "EXTRACTED", "source_file": "C:\\Users\\Keanghour\\Documents\\GitHub\\FNode\\FNode\\SupportProject\\sing-box\\experimental\\libbox\\tun.go", "source_location": "L10", "weight": 1.0, "context": "import"}, {"source": "c_users_keanghour_documents_github_fnode_fnode_supportproject_sing_box_experimental_libbox_tun_go", "target": "libbox_tunoptions", "relation": "contains", "confidence": "EXTRACTED", "source_file": "C:\\Users\\Keanghour\\Documents\\GitHub\\FNode\\FNode\\SupportProject\\sing-box\\experimental\\libbox\\tun.go", "source_location": "L13", "weight": 1.0}, {"source": "c_users_keanghour_documents_github_fnode_fnode_supportproject_sing_box_experimental_libbox_tun_go", "target": "libbox_routeprefix", "relation": "contains", "confidence": "EXTRACTED", "source_file": "C:\\Users\\Keanghour\\Documents\\GitHub\\FNode\\FNode\\SupportProject\\sing-box\\experimental\\libbox\\tun.go", "source_location": "L35", "weight": 1.0}, {"source": "libbox_routeprefix", "target": "libbox_routeprefix_address", "relation": "method", "confidence": "EXTRACTED", "source_file": "C:\\Users\\Keanghour\\Documents\\GitHub\\FNode\\FNode\\SupportProject\\sing-box\\experimental\\libbox\\tun.go", "source_location": "L40", "weight": 1.0}, {"source": "libbox_routeprefix", "target": "libbox_routeprefix_prefix", "relation": "method", "confidence": "EXTRACTED", "source_file": "C:\\Users\\Keanghour\\Documents\\GitHub\\FNode\\FNode\\SupportProject\\sing-box\\experimental\\libbox\\tun.go", "source_location": "L44", "weight": 1.0}, {"source": "libbox_routeprefix", "target": "libbox_routeprefix_mask", "relation": "method", "confidence": "EXTRACTED", "source_file": "C:\\Users\\Keanghour\\Documents\\GitHub\\FNode\\FNode\\SupportProject\\sing-box\\experimental\\libbox\\tun.go", "source_location": "L48", "weight": 1.0}, {"source": "libbox_routeprefix", "target": "libbox_routeprefix_string", "relation": "method", "confidence": "EXTRACTED", "source_file": "C:\\Users\\Keanghour\\Documents\\GitHub\\FNode\\FNode\\SupportProject\\sing-box\\experimental\\libbox\\tun.go", "source_location": "L58", "weight": 1.0}, {"source": "c_users_keanghour_documents_github_fnode_fnode_supportproject_sing_box_experimental_libbox_tun_go", "target": "libbox_routeprefixiterator", "relation": "contains", "confidence": "EXTRACTED", "source_file": "C:\\Users\\Keanghour\\Documents\\GitHub\\FNode\\FNode\\SupportProject\\sing-box\\experimental\\libbox\\tun.go", "source_location": "L62", "weight": 1.0}, {"source": "c_users_keanghour_documents_github_fnode_fnode_supportproject_sing_box_experimental_libbox_tun_go", "target": "libbox_tun_maprouteprefix", "relation": "contains", "confidence": "EXTRACTED", "source_file": "C:\\Users\\Keanghour\\Documents\\GitHub\\FNode\\FNode\\SupportProject\\sing-box\\experimental\\libbox\\tun.go", "source_location": "L67", "weight": 1.0}, {"source": "c_users_keanghour_documents_github_fnode_fnode_supportproject_sing_box_experimental_libbox_tun_go", "target": "libbox_tunoptions", "relation": "contains", "confidence": "EXTRACTED", "source_file": "C:\\Users\\Keanghour\\Documents\\GitHub\\FNode\\FNode\\SupportProject\\sing-box\\experimental\\libbox\\tun.go", "source_location": "L78", "weight": 1.0}, {"source": "libbox_tunoptions", "target": "libbox_tunoptions_getinet4address", "relation": "method", "confidence": "EXTRACTED", "source_file": "C:\\Users\\Keanghour\\Documents\\GitHub\\FNode\\FNode\\SupportProject\\sing-box\\experimental\\libbox\\tun.go", "source_location": "L84", "weight": 1.0}, {"source": "libbox_tunoptions", "target": "libbox_tunoptions_getinet6address", "relation": "method", "confidence": "EXTRACTED", "source_file": "C:\\Users\\Keanghour\\Documents\\GitHub\\FNode\\FNode\\SupportProject\\sing-box\\experimental\\libbox\\tun.go", "source_location": "L88", "weight": 1.0}, {"source": "libbox_tunoptions", "target": "libbox_tunoptions_getdnsserveraddress", "relation": "method", "confidence": "EXTRACTED", "source_file": "C:\\Users\\Keanghour\\Documents\\GitHub\\FNode\\FNode\\SupportProject\\sing-box\\experimental\\libbox\\tun.go", "source_location": "L92", "weight": 1.0}, {"source": "libbox_tunoptions", "target": "libbox_tunoptions_getmtu", "relation": "method", "confidence": "EXTRACTED", "source_file": "C:\\Users\\Keanghour\\Documents\\GitHub\\FNode\\FNode\\SupportProject\\sing-box\\experimental\\libbox\\tun.go", "source_location": "L99", "weight": 1.0}, {"source": "libbox_tunoptions", "target": "libbox_tunoptions_getautoroute", "relation": "method", "confidence": "EXTRACTED", "source_file": "C:\\Users\\Keanghour\\Documents\\GitHub\\FNode\\FNode\\SupportProject\\sing-box\\experimental\\libbox\\tun.go", "source_location": "L103", "weight": 1.0}, {"source": "libbox_tunoptions", "target": "libbox_tunoptions_getstrictroute", "relation": "method", "confidence": "EXTRACTED", "source_file": "C:\\Users\\Keanghour\\Documents\\GitHub\\FNode\\FNode\\SupportProject\\sing-box\\experimental\\libbox\\tun.go", "source_location": "L107", "weight": 1.0}, {"source": "libbox_tunoptions", "target": "libbox_tunoptions_getinet4routeaddress", "relation": "method", "confidence": "EXTRACTED", "source_file": "C:\\Users\\Keanghour\\Documents\\GitHub\\FNode\\FNode\\SupportProject\\sing-box\\experimental\\libbox\\tun.go", "source_location": "L111", "weight": 1.0}, {"source": "libbox_tunoptions", "target": "libbox_tunoptions_getinet6routeaddress", "relation": "method", "confidence": "EXTRACTED", "source_file": "C:\\Users\\Keanghour\\Documents\\GitHub\\FNode\\FNode\\SupportProject\\sing-box\\experimental\\libbox\\tun.go", "source_location": "L115", "weight": 1.0}, {"source": "libbox_tunoptions", "target": "libbox_tunoptions_getinet4routeexcludeaddress", "relation": "method", "confidence": "EXTRACTED", "source_file": "C:\\Users\\Keanghour\\Documents\\GitHub\\FNode\\FNode\\SupportProject\\sing-box\\experimental\\libbox\\tun.go", "source_location": "L119", "weight": 1.0}, {"source": "libbox_tunoptions", "target": "libbox_tunoptions_getinet6routeexcludeaddress", "relation": "method", "confidence": "EXTRACTED", "source_file": "C:\\Users\\Keanghour\\Documents\\GitHub\\FNode\\FNode\\SupportProject\\sing-box\\experimental\\libbox\\tun.go", "source_location": "L123", "weight": 1.0}, {"source": "libbox_tunoptions", "target": "libbox_tunoptions_getinet4routerange", "relation": "method", "confidence": "EXTRACTED", "source_file": "C:\\Users\\Keanghour\\Documents\\GitHub\\FNode\\FNode\\SupportProject\\sing-box\\experimental\\libbox\\tun.go", "source_location": "L127", "weight": 1.0}, {"source": "libbox_tunoptions", "target": "libbox_tunoptions_getinet6routerange", "relation": "method", "confidence": "EXTRACTED", "source_file": "C:\\Users\\Keanghour\\Documents\\GitHub\\FNode\\FNode\\SupportProject\\sing-box\\experimental\\libbox\\tun.go", "source_location": "L133", "weight": 1.0}, {"source": "libbox_tunoptions", "target": "libbox_tunoptions_getincludepackage", "relation": "method", "confidence": "EXTRACTED", "source_file": "C:\\Users\\Keanghour\\Documents\\GitHub\\FNode\\FNode\\SupportProject\\sing-box\\experimental\\libbox\\tun.go", "source_location": "L139", "weight": 1.0}, {"source": "libbox_tunoptions", "target": "libbox_tunoptions_getexcludepackage", "relation": "method", "confidence": "EXTRACTED", "source_file": "C:\\Users\\Keanghour\\Documents\\GitHub\\FNode\\FNode\\SupportProject\\sing-box\\experimental\\libbox\\tun.go", "source_location": "L143", "weight": 1.0}, {"source": "libbox_tunoptions", "target": "libbox_tunoptions_ishttpproxyenabled", "relation": "method", "confidence": "EXTRACTED", "source_file": "C:\\Users\\Keanghour\\Documents\\GitHub\\FNode\\FNode\\SupportProject\\sing-box\\experimental\\libbox\\tun.go", "source_location": "L147", "weight": 1.0}, {"source": "libbox_tunoptions", "target": "libbox_tunoptions_gethttpproxyserver", "relation": "method", "confidence": "EXTRACTED", "source_file": "C:\\Users\\Keanghour\\Documents\\GitHub\\FNode\\FNode\\SupportProject\\sing-box\\experimental\\libbox\\tun.go", "source_location": "L154", "weight": 1.0}, {"source": "libbox_tunoptions", "target": "libbox_tunoptions_gethttpproxyserverport", "relation": "method", "confidence": "EXTRACTED", "source_file": "C:\\Users\\Keanghour\\Documents\\GitHub\\FNode\\FNode\\SupportProject\\sing-box\\experimental\\libbox\\tun.go", "source_location": "L158", "weight": 1.0}, {"source": "libbox_tunoptions", "target": "libbox_tunoptions_gethttpproxybypassdomain", "relation": "method", "confidence": "EXTRACTED", "source_file": "C:\\Users\\Keanghour\\Documents\\GitHub\\FNode\\FNode\\SupportProject\\sing-box\\experimental\\libbox\\tun.go", "source_location": "L162", "weight": 1.0}, {"source": "libbox_tunoptions", "target": "libbox_tunoptions_gethttpproxymatchdomain", "relation": "method", "confidence": "EXTRACTED", "source_file": "C:\\Users\\Keanghour\\Documents\\GitHub\\FNode\\FNode\\SupportProject\\sing-box\\experimental\\libbox\\tun.go", "source_location": "L166", "weight": 1.0}, {"source": "libbox_routeprefix_address", "target": "libbox_routeprefix_string", "relation": "calls", "context": "call", "confidence": "EXTRACTED", "source_file": "C:\\Users\\Keanghour\\Documents\\GitHub\\FNode\\FNode\\SupportProject\\sing-box\\experimental\\libbox\\tun.go", "source_location": "L41", "weight": 1.0}, {"source": "libbox_routeprefix_mask", "target": "libbox_routeprefix_string", "relation": "calls", "context": "call", "confidence": "EXTRACTED", "source_file": "C:\\Users\\Keanghour\\Documents\\GitHub\\FNode\\FNode\\SupportProject\\sing-box\\experimental\\libbox\\tun.go", "source_location": "L55", "weight": 1.0}, {"source": "libbox_tunoptions_getinet4address", "target": "libbox_tun_maprouteprefix", "relation": "calls", "context": "call", "confidence": "EXTRACTED", "source_file": "C:\\Users\\Keanghour\\Documents\\GitHub\\FNode\\FNode\\SupportProject\\sing-box\\experimental\\libbox\\tun.go", "source_location": "L85", "weight": 1.0}, {"source": "libbox_tunoptions_getinet6address", "target": "libbox_tun_maprouteprefix", "relation": "calls", "context": "call", "confidence": "EXTRACTED", "source_file": "C:\\Users\\Keanghour\\Documents\\GitHub\\FNode\\FNode\\SupportProject\\sing-box\\experimental\\libbox\\tun.go", "source_location": "L89", "weight": 1.0}, {"source": "libbox_tunoptions_getdnsserveraddress", "target": "libbox_routeprefix_string", "relation": "calls", "context": "call", "confidence": "EXTRACTED", "source_file": "C:\\Users\\Keanghour\\Documents\\GitHub\\FNode\\FNode\\SupportProject\\sing-box\\experimental\\libbox\\tun.go", "source_location": "L96", "weight": 1.0}, {"source": "libbox_tunoptions_getinet4routeaddress", "target": "libbox_tun_maprouteprefix", "relation": "calls", "context": "call", "confidence": "EXTRACTED", "source_file": "C:\\Users\\Keanghour\\Documents\\GitHub\\FNode\\FNode\\SupportProject\\sing-box\\experimental\\libbox\\tun.go", "source_location": "L112", "weight": 1.0}, {"source": "libbox_tunoptions_getinet6routeaddress", "target": "libbox_tun_maprouteprefix", "relation": "calls", "context": "call", "confidence": "EXTRACTED", "source_file": "C:\\Users\\Keanghour\\Documents\\GitHub\\FNode\\FNode\\SupportProject\\sing-box\\experimental\\libbox\\tun.go", "source_location": "L116", "weight": 1.0}, {"source": "libbox_tunoptions_getinet4routeexcludeaddress", "target": "libbox_tun_maprouteprefix", "relation": "calls", "context": "call", "confidence": "EXTRACTED", "source_file": "C:\\Users\\Keanghour\\Documents\\GitHub\\FNode\\FNode\\SupportProject\\sing-box\\experimental\\libbox\\tun.go", "source_location": "L120", "weight": 1.0}, {"source": "libbox_tunoptions_getinet6routeexcludeaddress", "target": "libbox_tun_maprouteprefix", "relation": "calls", "context": "call", "confidence": "EXTRACTED", "source_file": "C:\\Users\\Keanghour\\Documents\\GitHub\\FNode\\FNode\\SupportProject\\sing-box\\experimental\\libbox\\tun.go", "source_location": "L124", "weight": 1.0}, {"source": "libbox_tunoptions_getinet4routerange", "target": "libbox_tun_maprouteprefix", "relation": "calls", "context": "call", "confidence": "EXTRACTED", "source_file": "C:\\Users\\Keanghour\\Documents\\GitHub\\FNode\\FNode\\SupportProject\\sing-box\\experimental\\libbox\\tun.go", "source_location": "L128", "weight": 1.0}, {"source": "libbox_tunoptions_getinet6routerange", "target": "libbox_tun_maprouteprefix", "relation": "calls", "context": "call", "confidence": "EXTRACTED", "source_file": "C:\\Users\\Keanghour\\Documents\\GitHub\\FNode\\FNode\\SupportProject\\sing-box\\experimental\\libbox\\tun.go", "source_location": "L134", "weight": 1.0}], "raw_calls": [{"caller_nid": "libbox_routeprefix_prefix", "callee": "int32", "is_member_call": false, "source_file": "C:\\Users\\Keanghour\\Documents\\GitHub\\FNode\\FNode\\SupportProject\\sing-box\\experimental\\libbox\\tun.go", "source_location": "L45"}, {"caller_nid": "libbox_routeprefix_mask", "callee": "Is6", "is_member_call": true, "source_file": "C:\\Users\\Keanghour\\Documents\\GitHub\\FNode\\FNode\\SupportProject\\sing-box\\experimental\\libbox\\tun.go", "source_location": "L50"}, {"caller_nid": "libbox_routeprefix_mask", "callee": "IP", "is_member_call": false, "source_file": "C:\\Users\\Keanghour\\Documents\\GitHub\\FNode\\FNode\\SupportProject\\sing-box\\experimental\\libbox\\tun.go", "source_location": "L55"}, {"caller_nid": "libbox_routeprefix_mask", "callee": "CIDRMask", "is_member_call": false, "source_file": "C:\\Users\\Keanghour\\Documents\\GitHub\\FNode\\FNode\\SupportProject\\sing-box\\experimental\\libbox\\tun.go", "source_location": "L55"}, {"caller_nid": "libbox_routeprefix_string", "callee": "String", "is_member_call": true, "source_file": "C:\\Users\\Keanghour\\Documents\\GitHub\\FNode\\FNode\\SupportProject\\sing-box\\experimental\\libbox\\tun.go", "source_location": "L59"}, {"caller_nid": "libbox_routeprefix_string", "callee": "PrefixFrom", "is_member_call": false, "source_file": "C:\\Users\\Keanghour\\Documents\\GitHub\\FNode\\FNode\\SupportProject\\sing-box\\experimental\\libbox\\tun.go", "source_location": "L59"}, {"caller_nid": "libbox_tun_maprouteprefix", "callee": "newIterator", "is_member_call": false, "source_file": "C:\\Users\\Keanghour\\Documents\\GitHub\\FNode\\FNode\\SupportProject\\sing-box\\experimental\\libbox\\tun.go", "source_location": "L68"}, {"caller_nid": "libbox_tun_maprouteprefix", "callee": "Map", "is_member_call": false, "source_file": "C:\\Users\\Keanghour\\Documents\\GitHub\\FNode\\FNode\\SupportProject\\sing-box\\experimental\\libbox\\tun.go", "source_location": "L68"}, {"caller_nid": "libbox_tun_maprouteprefix", "callee": "Addr", "is_member_call": true, "source_file": "C:\\Users\\Keanghour\\Documents\\GitHub\\FNode\\FNode\\SupportProject\\sing-box\\experimental\\libbox\\tun.go", "source_location": "L70"}, {"caller_nid": "libbox_tun_maprouteprefix", "callee": "Bits", "is_member_call": true, "source_file": "C:\\Users\\Keanghour\\Documents\\GitHub\\FNode\\FNode\\SupportProject\\sing-box\\experimental\\libbox\\tun.go", "source_location": "L71"}, {"caller_nid": "libbox_tunoptions_getdnsserveraddress", "callee": "len", "is_member_call": false, "source_file": "C:\\Users\\Keanghour\\Documents\\GitHub\\FNode\\FNode\\SupportProject\\sing-box\\experimental\\libbox\\tun.go", "source_location": "L93"}, {"caller_nid": "libbox_tunoptions_getdnsserveraddress", "callee": "Bits", "is_member_call": true, "source_file": "C:\\Users\\Keanghour\\Documents\\GitHub\\FNode\\FNode\\SupportProject\\sing-box\\experimental\\libbox\\tun.go", "source_location": "L93"}, {"caller_nid": "libbox_tunoptions_getdnsserveraddress", "callee": "New", "is_member_call": false, "source_file": "C:\\Users\\Keanghour\\Documents\\GitHub\\FNode\\FNode\\SupportProject\\sing-box\\experimental\\libbox\\tun.go", "source_location": "L94"}, {"caller_nid": "libbox_tunoptions_getdnsserveraddress", "callee": "wrapString", "is_member_call": false, "source_file": "C:\\Users\\Keanghour\\Documents\\GitHub\\FNode\\FNode\\SupportProject\\sing-box\\experimental\\libbox\\tun.go", "source_location": "L96"}, {"caller_nid": "libbox_tunoptions_getdnsserveraddress", "callee": "Next", "is_member_call": true, "source_file": "C:\\Users\\Keanghour\\Documents\\GitHub\\FNode\\FNode\\SupportProject\\sing-box\\experimental\\libbox\\tun.go", "source_location": "L96"}, {"caller_nid": "libbox_tunoptions_getdnsserveraddress", "callee": "Addr", "is_member_call": true, "source_file": "C:\\Users\\Keanghour\\Documents\\GitHub\\FNode\\FNode\\SupportProject\\sing-box\\experimental\\libbox\\tun.go", "source_location": "L96"}, {"caller_nid": "libbox_tunoptions_getmtu", "callee": "int32", "is_member_call": false, "source_file": "C:\\Users\\Keanghour\\Documents\\GitHub\\FNode\\FNode\\SupportProject\\sing-box\\experimental\\libbox\\tun.go", "source_location": "L100"}, {"caller_nid": "libbox_tunoptions_getinet4routerange", "callee": "Filter", "is_member_call": false, "source_file": "C:\\Users\\Keanghour\\Documents\\GitHub\\FNode\\FNode\\SupportProject\\sing-box\\experimental\\libbox\\tun.go", "source_location": "L128"}, {"caller_nid": "libbox_tunoptions_getinet4routerange", "callee": "Is4", "is_member_call": true, "source_file": "C:\\Users\\Keanghour\\Documents\\GitHub\\FNode\\FNode\\SupportProject\\sing-box\\experimental\\libbox\\tun.go", "source_location": "L129"}, {"caller_nid": "libbox_tunoptions_getinet4routerange", "callee": "Addr", "is_member_call": true, "source_file": "C:\\Users\\Keanghour\\Documents\\GitHub\\FNode\\FNode\\SupportProject\\sing-box\\experimental\\libbox\\tun.go", "source_location": "L129"}, {"caller_nid": "libbox_tunoptions_getinet6routerange", "callee": "Filter", "is_member_call": false, "source_file": "C:\\Users\\Keanghour\\Documents\\GitHub\\FNode\\FNode\\SupportProject\\sing-box\\experimental\\libbox\\tun.go", "source_location": "L134"}, {"caller_nid": "libbox_tunoptions_getinet6routerange", "callee": "Is6", "is_member_call": true, "source_file": "C:\\Users\\Keanghour\\Documents\\GitHub\\FNode\\FNode\\SupportProject\\sing-box\\experimental\\libbox\\tun.go", "source_location": "L135"}, {"caller_nid": "libbox_tunoptions_getinet6routerange", "callee": "Addr", "is_member_call": true, "source_file": "C:\\Users\\Keanghour\\Documents\\GitHub\\FNode\\FNode\\SupportProject\\sing-box\\experimental\\libbox\\tun.go", "source_location": "L135"}, {"caller_nid": "libbox_tunoptions_getincludepackage", "callee": "newIterator", "is_member_call": false, "source_file": "C:\\Users\\Keanghour\\Documents\\GitHub\\FNode\\FNode\\SupportProject\\sing-box\\experimental\\libbox\\tun.go", "source_location": "L140"}, {"caller_nid": "libbox_tunoptions_getexcludepackage", "callee": "newIterator", "is_member_call": false, "source_file": "C:\\Users\\Keanghour\\Documents\\GitHub\\FNode\\FNode\\SupportProject\\sing-box\\experimental\\libbox\\tun.go", "source_location": "L144"}, {"caller_nid": "libbox_tunoptions_gethttpproxyserverport", "callee": "int32", "is_member_call": false, "source_file": "C:\\Users\\Keanghour\\Documents\\GitHub\\FNode\\FNode\\SupportProject\\sing-box\\experimental\\libbox\\tun.go", "source_location": "L159"}, {"caller_nid": "libbox_tunoptions_gethttpproxybypassdomain", "callee": "newIterator", "is_member_call": false, "source_file": "C:\\Users\\Keanghour\\Documents\\GitHub\\FNode\\FNode\\SupportProject\\sing-box\\experimental\\libbox\\tun.go", "source_location": "L163"}, {"caller_nid": "libbox_tunoptions_gethttpproxymatchdomain", "callee": "newIterator", "is_member_call": false, "source_file": "C:\\Users\\Keanghour\\Documents\\GitHub\\FNode\\FNode\\SupportProject\\sing-box\\experimental\\libbox\\tun.go", "source_location": "L167"}]}