{"nodes": [{"id": "c_users_keanghour_documents_github_fnode_fnode_supportproject_sing_box_dns_transport_hosts_hosts_test_go", "label": "hosts_test.go", "file_type": "code", "source_file": "C:\\Users\\Keanghour\\Documents\\GitHub\\FNode\\FNode\\SupportProject\\sing-box\\dns\\transport\\hosts\\hosts_test.go", "source_location": "L1"}, {"id": "hosts_hosts_test_testhosts", "label": "TestHosts()", "file_type": "code", "source_file": "C:\\Users\\Keanghour\\Documents\\GitHub\\FNode\\FNode\\SupportProject\\sing-box\\dns\\transport\\hosts\\hosts_test.go", "source_location": "L12"}], "edges": [{"source": "c_users_keanghour_documents_github_fnode_fnode_supportproject_sing_box_dns_transport_hosts_hosts_test_go", "target": "go_pkg_net_netip", "relation": "imports_from", "confidence": "EXTRACTED", "source_file": "C:\\Users\\Keanghour\\Documents\\GitHub\\FNode\\FNode\\SupportProject\\sing-box\\dns\\transport\\hosts\\hosts_test.go", "source_location": "L4", "weight": 1.0, "context": "import"}, {"source": "c_users_keanghour_documents_github_fnode_fnode_supportproject_sing_box_dns_transport_hosts_hosts_test_go", "target": "go_pkg_testing", "relation": "imports_from", "confidence": "EXTRACTED", "source_file": "C:\\Users\\Keanghour\\Documents\\GitHub\\FNode\\FNode\\SupportProject\\sing-box\\dns\\transport\\hosts\\hosts_test.go", "source_location": "L5", "weight": 1.0, "context": "import"}, {"source": "c_users_keanghour_documents_github_fnode_fnode_supportproject_sing_box_dns_transport_hosts_hosts_test_go", "target": "go_pkg_github_com_sagernet_sing_box_dns_transport_hosts", "relation": "imports_from", "confidence": "EXTRACTED", "source_file": "C:\\Users\\Keanghour\\Documents\\GitHub\\FNode\\FNode\\SupportProject\\sing-box\\dns\\transport\\hosts\\hosts_test.go", "source_location": "L7", "weight": 1.0, "context": "import"}, {"source": "c_users_keanghour_documents_github_fnode_fnode_supportproject_sing_box_dns_transport_hosts_hosts_test_go", "target": "go_pkg_github_com_stretchr_testify_require", "relation": "imports_from", "confidence": "EXTRACTED", "source_file": "C:\\Users\\Keanghour\\Documents\\GitHub\\FNode\\FNode\\SupportProject\\sing-box\\dns\\transport\\hosts\\hosts_test.go", "source_location": "L9", "weight": 1.0, "context": "import"}, {"source": "c_users_keanghour_documents_github_fnode_fnode_supportproject_sing_box_dns_transport_hosts_hosts_test_go", "target": "hosts_hosts_test_testhosts", "relation": "contains", "confidence": "EXTRACTED", "source_file": "C:\\Users\\Keanghour\\Documents\\GitHub\\FNode\\FNode\\SupportProject\\sing-box\\dns\\transport\\hosts\\hosts_test.go", "source_location": "L12", "weight": 1.0}], "raw_calls": [{"caller_nid": "hosts_hosts_test_testhosts", "callee": "Parallel", "is_member_call": true, "source_file": "C:\\Users\\Keanghour\\Documents\\GitHub\\FNode\\FNode\\SupportProject\\sing-box\\dns\\transport\\hosts\\hosts_test.go", "source_location": "L13"}, {"caller_nid": "hosts_hosts_test_testhosts", "callee": "Equal", "is_member_call": false, "source_file": "C:\\Users\\Keanghour\\Documents\\GitHub\\FNode\\FNode\\SupportProject\\sing-box\\dns\\transport\\hosts\\hosts_test.go", "source_location": "L14"}, {"caller_nid": "hosts_hosts_test_testhosts", "callee": "AddrFrom4", "is_member_call": false, "source_file": "C:\\Users\\Keanghour\\Documents\\GitHub\\FNode\\FNode\\SupportProject\\sing-box\\dns\\transport\\hosts\\hosts_test.go", "source_location": "L14"}, {"caller_nid": "hosts_hosts_test_testhosts", "callee": "IPv6Loopback", "is_member_call": false, "source_file": "C:\\Users\\Keanghour\\Documents\\GitHub\\FNode\\FNode\\SupportProject\\sing-box\\dns\\transport\\hosts\\hosts_test.go", "source_location": "L14"}, {"caller_nid": "hosts_hosts_test_testhosts", "callee": "Lookup", "is_member_call": true, "source_file": "C:\\Users\\Keanghour\\Documents\\GitHub\\FNode\\FNode\\SupportProject\\sing-box\\dns\\transport\\hosts\\hosts_test.go", "source_location": "L14"}, {"caller_nid": "hosts_hosts_test_testhosts", "callee": "NewFile", "is_member_call": false, "source_file": "C:\\Users\\Keanghour\\Documents\\GitHub\\FNode\\FNode\\SupportProject\\sing-box\\dns\\transport\\hosts\\hosts_test.go", "source_location": "L14"}, {"caller_nid": "hosts_hosts_test_testhosts", "callee": "NotEmpty", "is_member_call": false, "source_file": "C:\\Users\\Keanghour\\Documents\\GitHub\\FNode\\FNode\\SupportProject\\sing-box\\dns\\transport\\hosts\\hosts_test.go", "source_location": "L15"}, {"caller_nid": "hosts_hosts_test_testhosts", "callee": "Lookup", "is_member_call": true, "source_file": "C:\\Users\\Keanghour\\Documents\\GitHub\\FNode\\FNode\\SupportProject\\sing-box\\dns\\transport\\hosts\\hosts_test.go", "source_location": "L15"}, {"caller_nid": "hosts_hosts_test_testhosts", "callee": "NewFile", "is_member_call": false, "source_file": "C:\\Users\\Keanghour\\Documents\\GitHub\\FNode\\FNode\\SupportProject\\sing-box\\dns\\transport\\hosts\\hosts_test.go", "source_location": "L15"}]}