{"nodes": [{"id": "c_users_keanghour_documents_github_fnode_fnode_supportproject_sing_box_common_tlsfragment_index_go", "label": "index.go", "file_type": "code", "source_file": "C:\\Users\\Keanghour\\Documents\\GitHub\\FNode\\FNode\\SupportProject\\sing-box\\common\\tlsfragment\\index.go", "source_location": "L1"}, {"id": "tlsfragment_myservername", "label": "MyServerName", "file_type": "code", "source_file": "C:\\Users\\Keanghour\\Documents\\GitHub\\FNode\\FNode\\SupportProject\\sing-box\\common\\tlsfragment\\index.go", "source_location": "L25"}, {"id": "tlsfragment_index_indextlsservername", "label": "IndexTLSServerName()", "file_type": "code", "source_file": "C:\\Users\\Keanghour\\Documents\\GitHub\\FNode\\FNode\\SupportProject\\sing-box\\common\\tlsfragment\\index.go", "source_location": "L31"}, {"id": "tlsfragment_index_indextlsservernamefromhandshake", "label": "indexTLSServerNameFromHandshake()", "file_type": "code", "source_file": "C:\\Users\\Keanghour\\Documents\\GitHub\\FNode\\FNode\\SupportProject\\sing-box\\common\\tlsfragment\\index.go", "source_location": "L47"}, {"id": "tlsfragment_index_indextlsservernamefromextensions", "label": "indexTLSServerNameFromExtensions()", "file_type": "code", "source_file": "C:\\Users\\Keanghour\\Documents\\GitHub\\FNode\\FNode\\SupportProject\\sing-box\\common\\tlsfragment\\index.go", "source_location": "L88"}], "edges": [{"source": "c_users_keanghour_documents_github_fnode_fnode_supportproject_sing_box_common_tlsfragment_index_go", "target": "go_pkg_encoding_binary", "relation": "imports_from", "confidence": "EXTRACTED", "source_file": "C:\\Users\\Keanghour\\Documents\\GitHub\\FNode\\FNode\\SupportProject\\sing-box\\common\\tlsfragment\\index.go", "source_location": "L4", "weight": 1.0, "context": "import"}, {"source": "c_users_keanghour_documents_github_fnode_fnode_supportproject_sing_box_common_tlsfragment_index_go", "target": "tlsfragment_myservername", "relation": "contains", "confidence": "EXTRACTED", "source_file": "C:\\Users\\Keanghour\\Documents\\GitHub\\FNode\\FNode\\SupportProject\\sing-box\\common\\tlsfragment\\index.go", "source_location": "L25", "weight": 1.0}, {"source": "c_users_keanghour_documents_github_fnode_fnode_supportproject_sing_box_common_tlsfragment_index_go", "target": "tlsfragment_index_indextlsservername", "relation": "contains", "confidence": "EXTRACTED", "source_file": "C:\\Users\\Keanghour\\Documents\\GitHub\\FNode\\FNode\\SupportProject\\sing-box\\common\\tlsfragment\\index.go", "source_location": "L31", "weight": 1.0}, {"source": "c_users_keanghour_documents_github_fnode_fnode_supportproject_sing_box_common_tlsfragment_index_go", "target": "tlsfragment_index_indextlsservernamefromhandshake", "relation": "contains", "confidence": "EXTRACTED", "source_file": "C:\\Users\\Keanghour\\Documents\\GitHub\\FNode\\FNode\\SupportProject\\sing-box\\common\\tlsfragment\\index.go", "source_location": "L47", "weight": 1.0}, {"source": "c_users_keanghour_documents_github_fnode_fnode_supportproject_sing_box_common_tlsfragment_index_go", "target": "tlsfragment_index_indextlsservernamefromextensions", "relation": "contains", "confidence": "EXTRACTED", "source_file": "C:\\Users\\Keanghour\\Documents\\GitHub\\FNode\\FNode\\SupportProject\\sing-box\\common\\tlsfragment\\index.go", "source_location": "L88", "weight": 1.0}, {"source": "tlsfragment_index_indextlsservername", "target": "tlsfragment_index_indextlsservernamefromhandshake", "relation": "calls", "context": "call", "confidence": "EXTRACTED", "source_file": "C:\\Users\\Keanghour\\Documents\\GitHub\\FNode\\FNode\\SupportProject\\sing-box\\common\\tlsfragment\\index.go", "source_location": "L39", "weight": 1.0}, {"source": "tlsfragment_index_indextlsservernamefromhandshake", "target": "tlsfragment_index_indextlsservernamefromextensions", "relation": "calls", "context": "call", "confidence": "EXTRACTED", "source_file": "C:\\Users\\Keanghour\\Documents\\GitHub\\FNode\\FNode\\SupportProject\\sing-box\\common\\tlsfragment\\index.go", "source_location": "L80", "weight": 1.0}], "raw_calls": [{"caller_nid": "tlsfragment_index_indextlsservername", "callee": "len", "is_member_call": false, "source_file": "C:\\Users\\Keanghour\\Documents\\GitHub\\FNode\\FNode\\SupportProject\\sing-box\\common\\tlsfragment\\index.go", "source_location": "L32"}, {"caller_nid": "tlsfragment_index_indextlsservername", "callee": "Uint16", "is_member_call": true, "source_file": "C:\\Users\\Keanghour\\Documents\\GitHub\\FNode\\FNode\\SupportProject\\sing-box\\common\\tlsfragment\\index.go", "source_location": "L35"}, {"caller_nid": "tlsfragment_index_indextlsservername", "callee": "len", "is_member_call": false, "source_file": "C:\\Users\\Keanghour\\Documents\\GitHub\\FNode\\FNode\\SupportProject\\sing-box\\common\\tlsfragment\\index.go", "source_location": "L36"}, {"caller_nid": "tlsfragment_index_indextlsservername", "callee": "int", "is_member_call": false, "source_file": "C:\\Users\\Keanghour\\Documents\\GitHub\\FNode\\FNode\\SupportProject\\sing-box\\common\\tlsfragment\\index.go", "source_location": "L36"}, {"caller_nid": "tlsfragment_index_indextlsservernamefromhandshake", "callee": "len", "is_member_call": false, "source_file": "C:\\Users\\Keanghour\\Documents\\GitHub\\FNode\\FNode\\SupportProject\\sing-box\\common\\tlsfragment\\index.go", "source_location": "L48"}, {"caller_nid": "tlsfragment_index_indextlsservernamefromhandshake", "callee": "uint32", "is_member_call": false, "source_file": "C:\\Users\\Keanghour\\Documents\\GitHub\\FNode\\FNode\\SupportProject\\sing-box\\common\\tlsfragment\\index.go", "source_location": "L54"}, {"caller_nid": "tlsfragment_index_indextlsservernamefromhandshake", "callee": "uint32", "is_member_call": false, "source_file": "C:\\Users\\Keanghour\\Documents\\GitHub\\FNode\\FNode\\SupportProject\\sing-box\\common\\tlsfragment\\index.go", "source_location": "L54"}, {"caller_nid": "tlsfragment_index_indextlsservernamefromhandshake", "callee": "uint32", "is_member_call": false, "source_file": "C:\\Users\\Keanghour\\Documents\\GitHub\\FNode\\FNode\\SupportProject\\sing-box\\common\\tlsfragment\\index.go", "source_location": "L54"}, {"caller_nid": "tlsfragment_index_indextlsservernamefromhandshake", "callee": "len", "is_member_call": false, "source_file": "C:\\Users\\Keanghour\\Documents\\GitHub\\FNode\\FNode\\SupportProject\\sing-box\\common\\tlsfragment\\index.go", "source_location": "L55"}, {"caller_nid": "tlsfragment_index_indextlsservernamefromhandshake", "callee": "int", "is_member_call": false, "source_file": "C:\\Users\\Keanghour\\Documents\\GitHub\\FNode\\FNode\\SupportProject\\sing-box\\common\\tlsfragment\\index.go", "source_location": "L55"}, {"caller_nid": "tlsfragment_index_indextlsservernamefromhandshake", "callee": "uint16", "is_member_call": false, "source_file": "C:\\Users\\Keanghour\\Documents\\GitHub\\FNode\\FNode\\SupportProject\\sing-box\\common\\tlsfragment\\index.go", "source_location": "L58"}, {"caller_nid": "tlsfragment_index_indextlsservernamefromhandshake", "callee": "uint16", "is_member_call": false, "source_file": "C:\\Users\\Keanghour\\Documents\\GitHub\\FNode\\FNode\\SupportProject\\sing-box\\common\\tlsfragment\\index.go", "source_location": "L58"}, {"caller_nid": "tlsfragment_index_indextlsservernamefromhandshake", "callee": "int", "is_member_call": false, "source_file": "C:\\Users\\Keanghour\\Documents\\GitHub\\FNode\\FNode\\SupportProject\\sing-box\\common\\tlsfragment\\index.go", "source_location": "L63"}, {"caller_nid": "tlsfragment_index_indextlsservernamefromhandshake", "callee": "len", "is_member_call": false, "source_file": "C:\\Users\\Keanghour\\Documents\\GitHub\\FNode\\FNode\\SupportProject\\sing-box\\common\\tlsfragment\\index.go", "source_location": "L64"}, {"caller_nid": "tlsfragment_index_indextlsservernamefromhandshake", "callee": "len", "is_member_call": false, "source_file": "C:\\Users\\Keanghour\\Documents\\GitHub\\FNode\\FNode\\SupportProject\\sing-box\\common\\tlsfragment\\index.go", "source_location": "L68"}, {"caller_nid": "tlsfragment_index_indextlsservernamefromhandshake", "callee": "uint16", "is_member_call": false, "source_file": "C:\\Users\\Keanghour\\Documents\\GitHub\\FNode\\FNode\\SupportProject\\sing-box\\common\\tlsfragment\\index.go", "source_location": "L71"}, {"caller_nid": "tlsfragment_index_indextlsservernamefromhandshake", "callee": "uint16", "is_member_call": false, "source_file": "C:\\Users\\Keanghour\\Documents\\GitHub\\FNode\\FNode\\SupportProject\\sing-box\\common\\tlsfragment\\index.go", "source_location": "L71"}, {"caller_nid": "tlsfragment_index_indextlsservernamefromhandshake", "callee": "len", "is_member_call": false, "source_file": "C:\\Users\\Keanghour\\Documents\\GitHub\\FNode\\FNode\\SupportProject\\sing-box\\common\\tlsfragment\\index.go", "source_location": "L72"}, {"caller_nid": "tlsfragment_index_indextlsservernamefromhandshake", "callee": "int", "is_member_call": false, "source_file": "C:\\Users\\Keanghour\\Documents\\GitHub\\FNode\\FNode\\SupportProject\\sing-box\\common\\tlsfragment\\index.go", "source_location": "L72"}, {"caller_nid": "tlsfragment_index_indextlsservernamefromhandshake", "callee": "uint16", "is_member_call": false, "source_file": "C:\\Users\\Keanghour\\Documents\\GitHub\\FNode\\FNode\\SupportProject\\sing-box\\common\\tlsfragment\\index.go", "source_location": "L75"}, {"caller_nid": "tlsfragment_index_indextlsservernamefromhandshake", "callee": "int", "is_member_call": false, "source_file": "C:\\Users\\Keanghour\\Documents\\GitHub\\FNode\\FNode\\SupportProject\\sing-box\\common\\tlsfragment\\index.go", "source_location": "L75"}, {"caller_nid": "tlsfragment_index_indextlsservernamefromhandshake", "callee": "int", "is_member_call": false, "source_file": "C:\\Users\\Keanghour\\Documents\\GitHub\\FNode\\FNode\\SupportProject\\sing-box\\common\\tlsfragment\\index.go", "source_location": "L76"}, {"caller_nid": "tlsfragment_index_indextlsservernamefromhandshake", "callee": "int", "is_member_call": false, "source_file": "C:\\Users\\Keanghour\\Documents\\GitHub\\FNode\\FNode\\SupportProject\\sing-box\\common\\tlsfragment\\index.go", "source_location": "L76"}, {"caller_nid": "tlsfragment_index_indextlsservernamefromhandshake", "callee": "len", "is_member_call": false, "source_file": "C:\\Users\\Keanghour\\Documents\\GitHub\\FNode\\FNode\\SupportProject\\sing-box\\common\\tlsfragment\\index.go", "source_location": "L77"}, {"caller_nid": "tlsfragment_index_indextlsservernamefromextensions", "callee": "len", "is_member_call": false, "source_file": "C:\\Users\\Keanghour\\Documents\\GitHub\\FNode\\FNode\\SupportProject\\sing-box\\common\\tlsfragment\\index.go", "source_location": "L89"}, {"caller_nid": "tlsfragment_index_indextlsservernamefromextensions", "callee": "len", "is_member_call": false, "source_file": "C:\\Users\\Keanghour\\Documents\\GitHub\\FNode\\FNode\\SupportProject\\sing-box\\common\\tlsfragment\\index.go", "source_location": "L92"}, {"caller_nid": "tlsfragment_index_indextlsservernamefromextensions", "callee": "uint16", "is_member_call": false, "source_file": "C:\\Users\\Keanghour\\Documents\\GitHub\\FNode\\FNode\\SupportProject\\sing-box\\common\\tlsfragment\\index.go", "source_location": "L95"}, {"caller_nid": "tlsfragment_index_indextlsservernamefromextensions", "callee": "uint16", "is_member_call": false, "source_file": "C:\\Users\\Keanghour\\Documents\\GitHub\\FNode\\FNode\\SupportProject\\sing-box\\common\\tlsfragment\\index.go", "source_location": "L95"}, {"caller_nid": "tlsfragment_index_indextlsservernamefromextensions", "callee": "len", "is_member_call": false, "source_file": "C:\\Users\\Keanghour\\Documents\\GitHub\\FNode\\FNode\\SupportProject\\sing-box\\common\\tlsfragment\\index.go", "source_location": "L97"}, {"caller_nid": "tlsfragment_index_indextlsservernamefromextensions", "callee": "int", "is_member_call": false, "source_file": "C:\\Users\\Keanghour\\Documents\\GitHub\\FNode\\FNode\\SupportProject\\sing-box\\common\\tlsfragment\\index.go", "source_location": "L97"}, {"caller_nid": "tlsfragment_index_indextlsservernamefromextensions", "callee": "len", "is_member_call": false, "source_file": "C:\\Users\\Keanghour\\Documents\\GitHub\\FNode\\FNode\\SupportProject\\sing-box\\common\\tlsfragment\\index.go", "source_location": "L100"}, {"caller_nid": "tlsfragment_index_indextlsservernamefromextensions", "callee": "len", "is_member_call": false, "source_file": "C:\\Users\\Keanghour\\Documents\\GitHub\\FNode\\FNode\\SupportProject\\sing-box\\common\\tlsfragment\\index.go", "source_location": "L101"}, {"caller_nid": "tlsfragment_index_indextlsservernamefromextensions", "callee": "uint16", "is_member_call": false, "source_file": "C:\\Users\\Keanghour\\Documents\\GitHub\\FNode\\FNode\\SupportProject\\sing-box\\common\\tlsfragment\\index.go", "source_location": "L104"}, {"caller_nid": "tlsfragment_index_indextlsservernamefromextensions", "callee": "uint16", "is_member_call": false, "source_file": "C:\\Users\\Keanghour\\Documents\\GitHub\\FNode\\FNode\\SupportProject\\sing-box\\common\\tlsfragment\\index.go", "source_location": "L104"}, {"caller_nid": "tlsfragment_index_indextlsservernamefromextensions", "callee": "uint16", "is_member_call": false, "source_file": "C:\\Users\\Keanghour\\Documents\\GitHub\\FNode\\FNode\\SupportProject\\sing-box\\common\\tlsfragment\\index.go", "source_location": "L105"}, {"caller_nid": "tlsfragment_index_indextlsservernamefromextensions", "callee": "uint16", "is_member_call": false, "source_file": "C:\\Users\\Keanghour\\Documents\\GitHub\\FNode\\FNode\\SupportProject\\sing-box\\common\\tlsfragment\\index.go", "source_location": "L105"}, {"caller_nid": "tlsfragment_index_indextlsservernamefromextensions", "callee": "len", "is_member_call": false, "source_file": "C:\\Users\\Keanghour\\Documents\\GitHub\\FNode\\FNode\\SupportProject\\sing-box\\common\\tlsfragment\\index.go", "source_location": "L106"}, {"caller_nid": "tlsfragment_index_indextlsservernamefromextensions", "callee": "int", "is_member_call": false, "source_file": "C:\\Users\\Keanghour\\Documents\\GitHub\\FNode\\FNode\\SupportProject\\sing-box\\common\\tlsfragment\\index.go", "source_location": "L106"}, {"caller_nid": "tlsfragment_index_indextlsservernamefromextensions", "callee": "int", "is_member_call": false, "source_file": "C:\\Users\\Keanghour\\Documents\\GitHub\\FNode\\FNode\\SupportProject\\sing-box\\common\\tlsfragment\\index.go", "source_location": "L109"}, {"caller_nid": "tlsfragment_index_indextlsservernamefromextensions", "callee": "len", "is_member_call": false, "source_file": "C:\\Users\\Keanghour\\Documents\\GitHub\\FNode\\FNode\\SupportProject\\sing-box\\common\\tlsfragment\\index.go", "source_location": "L113"}, {"caller_nid": "tlsfragment_index_indextlsservernamefromextensions", "callee": "uint16", "is_member_call": false, "source_file": "C:\\Users\\Keanghour\\Documents\\GitHub\\FNode\\FNode\\SupportProject\\sing-box\\common\\tlsfragment\\index.go", "source_location": "L120"}, {"caller_nid": "tlsfragment_index_indextlsservernamefromextensions", "callee": "uint16", "is_member_call": false, "source_file": "C:\\Users\\Keanghour\\Documents\\GitHub\\FNode\\FNode\\SupportProject\\sing-box\\common\\tlsfragment\\index.go", "source_location": "L120"}, {"caller_nid": "tlsfragment_index_indextlsservernamefromextensions", "callee": "int", "is_member_call": false, "source_file": "C:\\Users\\Keanghour\\Documents\\GitHub\\FNode\\FNode\\SupportProject\\sing-box\\common\\tlsfragment\\index.go", "source_location": "L125"}, {"caller_nid": "tlsfragment_index_indextlsservernamefromextensions", "callee": "string", "is_member_call": false, "source_file": "C:\\Users\\Keanghour\\Documents\\GitHub\\FNode\\FNode\\SupportProject\\sing-box\\common\\tlsfragment\\index.go", "source_location": "L126"}, {"caller_nid": "tlsfragment_index_indextlsservernamefromextensions", "callee": "int", "is_member_call": false, "source_file": "C:\\Users\\Keanghour\\Documents\\GitHub\\FNode\\FNode\\SupportProject\\sing-box\\common\\tlsfragment\\index.go", "source_location": "L130"}]}