{"nodes": [{"id": "c_users_keanghour_documents_github_fnode_fnode_supportproject_sing_box_transport_v2ray_transport_go", "label": "transport.go", "file_type": "code", "source_file": "C:\\Users\\Keanghour\\Documents\\GitHub\\FNode\\FNode\\SupportProject\\sing-box\\transport\\v2ray\\transport.go", "source_location": "L1"}, {"id": "v2ray_serverconstructor", "label": "ServerConstructor", "file_type": "code", "source_file": "C:\\Users\\Keanghour\\Documents\\GitHub\\FNode\\FNode\\SupportProject\\sing-box\\transport\\v2ray\\transport.go", "source_location": "L20"}, {"id": "v2ray_clientconstructor", "label": "ClientConstructor", "file_type": "code", "source_file": "C:\\Users\\Keanghour\\Documents\\GitHub\\FNode\\FNode\\SupportProject\\sing-box\\transport\\v2ray\\transport.go", "source_location": "L21"}, {"id": "v2ray_transport_newservertransport", "label": "NewServerTransport()", "file_type": "code", "source_file": "C:\\Users\\Keanghour\\Documents\\GitHub\\FNode\\FNode\\SupportProject\\sing-box\\transport\\v2ray\\transport.go", "source_location": "L24"}, {"id": "v2ray_transport_newclienttransport", "label": "NewClientTransport()", "file_type": "code", "source_file": "C:\\Users\\Keanghour\\Documents\\GitHub\\FNode\\FNode\\SupportProject\\sing-box\\transport\\v2ray\\transport.go", "source_location": "L47"}], "edges": [{"source": "c_users_keanghour_documents_github_fnode_fnode_supportproject_sing_box_transport_v2ray_transport_go", "target": "go_pkg_context", "relation": "imports_from", "confidence": "EXTRACTED", "source_file": "C:\\Users\\Keanghour\\Documents\\GitHub\\FNode\\FNode\\SupportProject\\sing-box\\transport\\v2ray\\transport.go", "source_location": "L4", "weight": 1.0, "context": "import"}, {"source": "c_users_keanghour_documents_github_fnode_fnode_supportproject_sing_box_transport_v2ray_transport_go", "target": "go_pkg_github_com_sagernet_sing_box_adapter", "relation": "imports_from", "confidence": "EXTRACTED", "source_file": "C:\\Users\\Keanghour\\Documents\\GitHub\\FNode\\FNode\\SupportProject\\sing-box\\transport\\v2ray\\transport.go", "source_location": "L6", "weight": 1.0, "context": "import"}, {"source": "c_users_keanghour_documents_github_fnode_fnode_supportproject_sing_box_transport_v2ray_transport_go", "target": "go_pkg_github_com_sagernet_sing_box_common_tls", "relation": "imports_from", "confidence": "EXTRACTED", "source_file": "C:\\Users\\Keanghour\\Documents\\GitHub\\FNode\\FNode\\SupportProject\\sing-box\\transport\\v2ray\\transport.go", "source_location": "L7", "weight": 1.0, "context": "import"}, {"source": "c_users_keanghour_documents_github_fnode_fnode_supportproject_sing_box_transport_v2ray_transport_go", "target": "go_pkg_github_com_sagernet_sing_box_constant", "relation": "imports_from", "confidence": "EXTRACTED", "source_file": "C:\\Users\\Keanghour\\Documents\\GitHub\\FNode\\FNode\\SupportProject\\sing-box\\transport\\v2ray\\transport.go", "source_location": "L8", "weight": 1.0, "context": "import"}, {"source": "c_users_keanghour_documents_github_fnode_fnode_supportproject_sing_box_transport_v2ray_transport_go", "target": "go_pkg_github_com_sagernet_sing_box_option", "relation": "imports_from", "confidence": "EXTRACTED", "source_file": "C:\\Users\\Keanghour\\Documents\\GitHub\\FNode\\FNode\\SupportProject\\sing-box\\transport\\v2ray\\transport.go", "source_location": "L9", "weight": 1.0, "context": "import"}, {"source": "c_users_keanghour_documents_github_fnode_fnode_supportproject_sing_box_transport_v2ray_transport_go", "target": "go_pkg_github_com_sagernet_sing_box_transport_v2rayhttp", "relation": "imports_from", "confidence": "EXTRACTED", "source_file": "C:\\Users\\Keanghour\\Documents\\GitHub\\FNode\\FNode\\SupportProject\\sing-box\\transport\\v2ray\\transport.go", "source_location": "L10", "weight": 1.0, "context": "import"}, {"source": "c_users_keanghour_documents_github_fnode_fnode_supportproject_sing_box_transport_v2ray_transport_go", "target": "go_pkg_github_com_sagernet_sing_box_transport_v2rayhttpupgrade", "relation": "imports_from", "confidence": "EXTRACTED", "source_file": "C:\\Users\\Keanghour\\Documents\\GitHub\\FNode\\FNode\\SupportProject\\sing-box\\transport\\v2ray\\transport.go", "source_location": "L11", "weight": 1.0, "context": "import"}, {"source": "c_users_keanghour_documents_github_fnode_fnode_supportproject_sing_box_transport_v2ray_transport_go", "target": "go_pkg_github_com_sagernet_sing_box_transport_v2raywebsocket", "relation": "imports_from", "confidence": "EXTRACTED", "source_file": "C:\\Users\\Keanghour\\Documents\\GitHub\\FNode\\FNode\\SupportProject\\sing-box\\transport\\v2ray\\transport.go", "source_location": "L12", "weight": 1.0, "context": "import"}, {"source": "c_users_keanghour_documents_github_fnode_fnode_supportproject_sing_box_transport_v2ray_transport_go", "target": "go_pkg_github_com_sagernet_sing_common_exceptions", "relation": "imports_from", "confidence": "EXTRACTED", "source_file": "C:\\Users\\Keanghour\\Documents\\GitHub\\FNode\\FNode\\SupportProject\\sing-box\\transport\\v2ray\\transport.go", "source_location": "L13", "weight": 1.0, "context": "import"}, {"source": "c_users_keanghour_documents_github_fnode_fnode_supportproject_sing_box_transport_v2ray_transport_go", "target": "go_pkg_github_com_sagernet_sing_common_logger", "relation": "imports_from", "confidence": "EXTRACTED", "source_file": "C:\\Users\\Keanghour\\Documents\\GitHub\\FNode\\FNode\\SupportProject\\sing-box\\transport\\v2ray\\transport.go", "source_location": "L14", "weight": 1.0, "context": "import"}, {"source": "c_users_keanghour_documents_github_fnode_fnode_supportproject_sing_box_transport_v2ray_transport_go", "target": "go_pkg_github_com_sagernet_sing_common_metadata", "relation": "imports_from", "confidence": "EXTRACTED", "source_file": "C:\\Users\\Keanghour\\Documents\\GitHub\\FNode\\FNode\\SupportProject\\sing-box\\transport\\v2ray\\transport.go", "source_location": "L15", "weight": 1.0, "context": "import"}, {"source": "c_users_keanghour_documents_github_fnode_fnode_supportproject_sing_box_transport_v2ray_transport_go", "target": "go_pkg_github_com_sagernet_sing_common_network", "relation": "imports_from", "confidence": "EXTRACTED", "source_file": "C:\\Users\\Keanghour\\Documents\\GitHub\\FNode\\FNode\\SupportProject\\sing-box\\transport\\v2ray\\transport.go", "source_location": "L16", "weight": 1.0, "context": "import"}, {"source": "c_users_keanghour_documents_github_fnode_fnode_supportproject_sing_box_transport_v2ray_transport_go", "target": "v2ray_serverconstructor", "relation": "contains", "confidence": "EXTRACTED", "source_file": "C:\\Users\\Keanghour\\Documents\\GitHub\\FNode\\FNode\\SupportProject\\sing-box\\transport\\v2ray\\transport.go", "source_location": "L20", "weight": 1.0}, {"source": "c_users_keanghour_documents_github_fnode_fnode_supportproject_sing_box_transport_v2ray_transport_go", "target": "v2ray_clientconstructor", "relation": "contains", "confidence": "EXTRACTED", "source_file": "C:\\Users\\Keanghour\\Documents\\GitHub\\FNode\\FNode\\SupportProject\\sing-box\\transport\\v2ray\\transport.go", "source_location": "L21", "weight": 1.0}, {"source": "c_users_keanghour_documents_github_fnode_fnode_supportproject_sing_box_transport_v2ray_transport_go", "target": "v2ray_transport_newservertransport", "relation": "contains", "confidence": "EXTRACTED", "source_file": "C:\\Users\\Keanghour\\Documents\\GitHub\\FNode\\FNode\\SupportProject\\sing-box\\transport\\v2ray\\transport.go", "source_location": "L24", "weight": 1.0}, {"source": "c_users_keanghour_documents_github_fnode_fnode_supportproject_sing_box_transport_v2ray_transport_go", "target": "v2ray_transport_newclienttransport", "relation": "contains", "confidence": "EXTRACTED", "source_file": "C:\\Users\\Keanghour\\Documents\\GitHub\\FNode\\FNode\\SupportProject\\sing-box\\transport\\v2ray\\transport.go", "source_location": "L47", "weight": 1.0}], "raw_calls": [{"caller_nid": "v2ray_transport_newservertransport", "callee": "NewServer", "is_member_call": false, "source_file": "C:\\Users\\Keanghour\\Documents\\GitHub\\FNode\\FNode\\SupportProject\\sing-box\\transport\\v2ray\\transport.go", "source_location": "L30"}, {"caller_nid": "v2ray_transport_newservertransport", "callee": "NewServer", "is_member_call": false, "source_file": "C:\\Users\\Keanghour\\Documents\\GitHub\\FNode\\FNode\\SupportProject\\sing-box\\transport\\v2ray\\transport.go", "source_location": "L32"}, {"caller_nid": "v2ray_transport_newservertransport", "callee": "NewQUICServer", "is_member_call": false, "source_file": "C:\\Users\\Keanghour\\Documents\\GitHub\\FNode\\FNode\\SupportProject\\sing-box\\transport\\v2ray\\transport.go", "source_location": "L37"}, {"caller_nid": "v2ray_transport_newservertransport", "callee": "NewGRPCServer", "is_member_call": false, "source_file": "C:\\Users\\Keanghour\\Documents\\GitHub\\FNode\\FNode\\SupportProject\\sing-box\\transport\\v2ray\\transport.go", "source_location": "L39"}, {"caller_nid": "v2ray_transport_newservertransport", "callee": "NewServer", "is_member_call": false, "source_file": "C:\\Users\\Keanghour\\Documents\\GitHub\\FNode\\FNode\\SupportProject\\sing-box\\transport\\v2ray\\transport.go", "source_location": "L41"}, {"caller_nid": "v2ray_transport_newservertransport", "callee": "New", "is_member_call": false, "source_file": "C:\\Users\\Keanghour\\Documents\\GitHub\\FNode\\FNode\\SupportProject\\sing-box\\transport\\v2ray\\transport.go", "source_location": "L43"}, {"caller_nid": "v2ray_transport_newclienttransport", "callee": "NewClient", "is_member_call": false, "source_file": "C:\\Users\\Keanghour\\Documents\\GitHub\\FNode\\FNode\\SupportProject\\sing-box\\transport\\v2ray\\transport.go", "source_location": "L53"}, {"caller_nid": "v2ray_transport_newclienttransport", "callee": "NewGRPCClient", "is_member_call": false, "source_file": "C:\\Users\\Keanghour\\Documents\\GitHub\\FNode\\FNode\\SupportProject\\sing-box\\transport\\v2ray\\transport.go", "source_location": "L55"}, {"caller_nid": "v2ray_transport_newclienttransport", "callee": "NewClient", "is_member_call": false, "source_file": "C:\\Users\\Keanghour\\Documents\\GitHub\\FNode\\FNode\\SupportProject\\sing-box\\transport\\v2ray\\transport.go", "source_location": "L57"}, {"caller_nid": "v2ray_transport_newclienttransport", "callee": "NewQUICClient", "is_member_call": false, "source_file": "C:\\Users\\Keanghour\\Documents\\GitHub\\FNode\\FNode\\SupportProject\\sing-box\\transport\\v2ray\\transport.go", "source_location": "L62"}, {"caller_nid": "v2ray_transport_newclienttransport", "callee": "NewClient", "is_member_call": false, "source_file": "C:\\Users\\Keanghour\\Documents\\GitHub\\FNode\\FNode\\SupportProject\\sing-box\\transport\\v2ray\\transport.go", "source_location": "L64"}, {"caller_nid": "v2ray_transport_newclienttransport", "callee": "New", "is_member_call": false, "source_file": "C:\\Users\\Keanghour\\Documents\\GitHub\\FNode\\FNode\\SupportProject\\sing-box\\transport\\v2ray\\transport.go", "source_location": "L66"}]}