{"nodes": [{"id": "c_users_keanghour_documents_github_fnode_fnode_supportproject_sing_box_common_tls_acme_go", "label": "acme.go", "file_type": "code", "source_file": "C:\\Users\\Keanghour\\Documents\\GitHub\\FNode\\FNode\\SupportProject\\sing-box\\common\\tls\\acme.go", "source_location": "L1"}, {"id": "tls_acmewrapper", "label": "acmeWrapper", "file_type": "code", "source_file": "C:\\Users\\Keanghour\\Documents\\GitHub\\FNode\\FNode\\SupportProject\\sing-box\\common\\tls\\acme.go", "source_location": "L25"}, {"id": "tls_acmewrapper_start", "label": ".Start()", "file_type": "code", "source_file": "C:\\Users\\Keanghour\\Documents\\GitHub\\FNode\\FNode\\SupportProject\\sing-box\\common\\tls\\acme.go", "source_location": "L32"}, {"id": "tls_acmewrapper_close", "label": ".Close()", "file_type": "code", "source_file": "C:\\Users\\Keanghour\\Documents\\GitHub\\FNode\\FNode\\SupportProject\\sing-box\\common\\tls\\acme.go", "source_location": "L36"}, {"id": "tls_acmelogwriter", "label": "acmeLogWriter", "file_type": "code", "source_file": "C:\\Users\\Keanghour\\Documents\\GitHub\\FNode\\FNode\\SupportProject\\sing-box\\common\\tls\\acme.go", "source_location": "L41"}, {"id": "tls_acmelogwriter_write", "label": ".Write()", "file_type": "code", "source_file": "C:\\Users\\Keanghour\\Documents\\GitHub\\FNode\\FNode\\SupportProject\\sing-box\\common\\tls\\acme.go", "source_location": "L45"}, {"id": "tls_acmelogwriter_sync", "label": ".Sync()", "file_type": "code", "source_file": "C:\\Users\\Keanghour\\Documents\\GitHub\\FNode\\FNode\\SupportProject\\sing-box\\common\\tls\\acme.go", "source_location": "L62"}, {"id": "tls_acme_encoderconfig", "label": "encoderConfig()", "file_type": "code", "source_file": "C:\\Users\\Keanghour\\Documents\\GitHub\\FNode\\FNode\\SupportProject\\sing-box\\common\\tls\\acme.go", "source_location": "L66"}, {"id": "tls_acme_startacme", "label": "startACME()", "file_type": "code", "source_file": "C:\\Users\\Keanghour\\Documents\\GitHub\\FNode\\FNode\\SupportProject\\sing-box\\common\\tls\\acme.go", "source_location": "L72"}], "edges": [{"source": "c_users_keanghour_documents_github_fnode_fnode_supportproject_sing_box_common_tls_acme_go", "target": "go_pkg_context", "relation": "imports_from", "confidence": "EXTRACTED", "source_file": "C:\\Users\\Keanghour\\Documents\\GitHub\\FNode\\FNode\\SupportProject\\sing-box\\common\\tls\\acme.go", "source_location": "L6", "weight": 1.0, "context": "import"}, {"source": "c_users_keanghour_documents_github_fnode_fnode_supportproject_sing_box_common_tls_acme_go", "target": "go_pkg_crypto_tls", "relation": "imports_from", "confidence": "EXTRACTED", "source_file": "C:\\Users\\Keanghour\\Documents\\GitHub\\FNode\\FNode\\SupportProject\\sing-box\\common\\tls\\acme.go", "source_location": "L7", "weight": 1.0, "context": "import"}, {"source": "c_users_keanghour_documents_github_fnode_fnode_supportproject_sing_box_common_tls_acme_go", "target": "go_pkg_strings", "relation": "imports_from", "confidence": "EXTRACTED", "source_file": "C:\\Users\\Keanghour\\Documents\\GitHub\\FNode\\FNode\\SupportProject\\sing-box\\common\\tls\\acme.go", "source_location": "L8", "weight": 1.0, "context": "import"}, {"source": "c_users_keanghour_documents_github_fnode_fnode_supportproject_sing_box_common_tls_acme_go", "target": "go_pkg_github_com_sagernet_sing_box_adapter", "relation": "imports_from", "confidence": "EXTRACTED", "source_file": "C:\\Users\\Keanghour\\Documents\\GitHub\\FNode\\FNode\\SupportProject\\sing-box\\common\\tls\\acme.go", "source_location": "L10", "weight": 1.0, "context": "import"}, {"source": "c_users_keanghour_documents_github_fnode_fnode_supportproject_sing_box_common_tls_acme_go", "target": "go_pkg_github_com_sagernet_sing_box_constant", "relation": "imports_from", "confidence": "EXTRACTED", "source_file": "C:\\Users\\Keanghour\\Documents\\GitHub\\FNode\\FNode\\SupportProject\\sing-box\\common\\tls\\acme.go", "source_location": "L11", "weight": 1.0, "context": "import"}, {"source": "c_users_keanghour_documents_github_fnode_fnode_supportproject_sing_box_common_tls_acme_go", "target": "go_pkg_github_com_sagernet_sing_box_option", "relation": "imports_from", "confidence": "EXTRACTED", "source_file": "C:\\Users\\Keanghour\\Documents\\GitHub\\FNode\\FNode\\SupportProject\\sing-box\\common\\tls\\acme.go", "source_location": "L12", "weight": 1.0, "context": "import"}, {"source": "c_users_keanghour_documents_github_fnode_fnode_supportproject_sing_box_common_tls_acme_go", "target": "go_pkg_github_com_sagernet_sing_common_exceptions", "relation": "imports_from", "confidence": "EXTRACTED", "source_file": "C:\\Users\\Keanghour\\Documents\\GitHub\\FNode\\FNode\\SupportProject\\sing-box\\common\\tls\\acme.go", "source_location": "L13", "weight": 1.0, "context": "import"}, {"source": "c_users_keanghour_documents_github_fnode_fnode_supportproject_sing_box_common_tls_acme_go", "target": "go_pkg_github_com_sagernet_sing_common_logger", "relation": "imports_from", "confidence": "EXTRACTED", "source_file": "C:\\Users\\Keanghour\\Documents\\GitHub\\FNode\\FNode\\SupportProject\\sing-box\\common\\tls\\acme.go", "source_location": "L14", "weight": 1.0, "context": "import"}, {"source": "c_users_keanghour_documents_github_fnode_fnode_supportproject_sing_box_common_tls_acme_go", "target": "go_pkg_github_com_caddyserver_certmagic", "relation": "imports_from", "confidence": "EXTRACTED", "source_file": "C:\\Users\\Keanghour\\Documents\\GitHub\\FNode\\FNode\\SupportProject\\sing-box\\common\\tls\\acme.go", "source_location": "L16", "weight": 1.0, "context": "import"}, {"source": "c_users_keanghour_documents_github_fnode_fnode_supportproject_sing_box_common_tls_acme_go", "target": "go_pkg_github_com_libdns_acmedns", "relation": "imports_from", "confidence": "EXTRACTED", "source_file": "C:\\Users\\Keanghour\\Documents\\GitHub\\FNode\\FNode\\SupportProject\\sing-box\\common\\tls\\acme.go", "source_location": "L17", "weight": 1.0, "context": "import"}, {"source": "c_users_keanghour_documents_github_fnode_fnode_supportproject_sing_box_common_tls_acme_go", "target": "go_pkg_github_com_libdns_alidns", "relation": "imports_from", "confidence": "EXTRACTED", "source_file": "C:\\Users\\Keanghour\\Documents\\GitHub\\FNode\\FNode\\SupportProject\\sing-box\\common\\tls\\acme.go", "source_location": "L18", "weight": 1.0, "context": "import"}, {"source": "c_users_keanghour_documents_github_fnode_fnode_supportproject_sing_box_common_tls_acme_go", "target": "go_pkg_github_com_libdns_cloudflare", "relation": "imports_from", "confidence": "EXTRACTED", "source_file": "C:\\Users\\Keanghour\\Documents\\GitHub\\FNode\\FNode\\SupportProject\\sing-box\\common\\tls\\acme.go", "source_location": "L19", "weight": 1.0, "context": "import"}, {"source": "c_users_keanghour_documents_github_fnode_fnode_supportproject_sing_box_common_tls_acme_go", "target": "go_pkg_github_com_mholt_acmez_v3_acme", "relation": "imports_from", "confidence": "EXTRACTED", "source_file": "C:\\Users\\Keanghour\\Documents\\GitHub\\FNode\\FNode\\SupportProject\\sing-box\\common\\tls\\acme.go", "source_location": "L20", "weight": 1.0, "context": "import"}, {"source": "c_users_keanghour_documents_github_fnode_fnode_supportproject_sing_box_common_tls_acme_go", "target": "go_pkg_go_uber_org_zap", "relation": "imports_from", "confidence": "EXTRACTED", "source_file": "C:\\Users\\Keanghour\\Documents\\GitHub\\FNode\\FNode\\SupportProject\\sing-box\\common\\tls\\acme.go", "source_location": "L21", "weight": 1.0, "context": "import"}, {"source": "c_users_keanghour_documents_github_fnode_fnode_supportproject_sing_box_common_tls_acme_go", "target": "go_pkg_go_uber_org_zap_zapcore", "relation": "imports_from", "confidence": "EXTRACTED", "source_file": "C:\\Users\\Keanghour\\Documents\\GitHub\\FNode\\FNode\\SupportProject\\sing-box\\common\\tls\\acme.go", "source_location": "L22", "weight": 1.0, "context": "import"}, {"source": "c_users_keanghour_documents_github_fnode_fnode_supportproject_sing_box_common_tls_acme_go", "target": "tls_acmewrapper", "relation": "contains", "confidence": "EXTRACTED", "source_file": "C:\\Users\\Keanghour\\Documents\\GitHub\\FNode\\FNode\\SupportProject\\sing-box\\common\\tls\\acme.go", "source_location": "L25", "weight": 1.0}, {"source": "tls_acmewrapper", "target": "tls_acmewrapper_start", "relation": "method", "confidence": "EXTRACTED", "source_file": "C:\\Users\\Keanghour\\Documents\\GitHub\\FNode\\FNode\\SupportProject\\sing-box\\common\\tls\\acme.go", "source_location": "L32", "weight": 1.0}, {"source": "tls_acmewrapper", "target": "tls_acmewrapper_close", "relation": "method", "confidence": "EXTRACTED", "source_file": "C:\\Users\\Keanghour\\Documents\\GitHub\\FNode\\FNode\\SupportProject\\sing-box\\common\\tls\\acme.go", "source_location": "L36", "weight": 1.0}, {"source": "c_users_keanghour_documents_github_fnode_fnode_supportproject_sing_box_common_tls_acme_go", "target": "tls_acmelogwriter", "relation": "contains", "confidence": "EXTRACTED", "source_file": "C:\\Users\\Keanghour\\Documents\\GitHub\\FNode\\FNode\\SupportProject\\sing-box\\common\\tls\\acme.go", "source_location": "L41", "weight": 1.0}, {"source": "tls_acmelogwriter", "target": "tls_acmelogwriter_write", "relation": "method", "confidence": "EXTRACTED", "source_file": "C:\\Users\\Keanghour\\Documents\\GitHub\\FNode\\FNode\\SupportProject\\sing-box\\common\\tls\\acme.go", "source_location": "L45", "weight": 1.0}, {"source": "tls_acmelogwriter", "target": "tls_acmelogwriter_sync", "relation": "method", "confidence": "EXTRACTED", "source_file": "C:\\Users\\Keanghour\\Documents\\GitHub\\FNode\\FNode\\SupportProject\\sing-box\\common\\tls\\acme.go", "source_location": "L62", "weight": 1.0}, {"source": "c_users_keanghour_documents_github_fnode_fnode_supportproject_sing_box_common_tls_acme_go", "target": "tls_acme_encoderconfig", "relation": "contains", "confidence": "EXTRACTED", "source_file": "C:\\Users\\Keanghour\\Documents\\GitHub\\FNode\\FNode\\SupportProject\\sing-box\\common\\tls\\acme.go", "source_location": "L66", "weight": 1.0}, {"source": "c_users_keanghour_documents_github_fnode_fnode_supportproject_sing_box_common_tls_acme_go", "target": "tls_acme_startacme", "relation": "contains", "confidence": "EXTRACTED", "source_file": "C:\\Users\\Keanghour\\Documents\\GitHub\\FNode\\FNode\\SupportProject\\sing-box\\common\\tls\\acme.go", "source_location": "L72", "weight": 1.0}, {"source": "tls_acme_startacme", "target": "tls_acme_encoderconfig", "relation": "calls", "context": "call", "confidence": "EXTRACTED", "source_file": "C:\\Users\\Keanghour\\Documents\\GitHub\\FNode\\FNode\\SupportProject\\sing-box\\common\\tls\\acme.go", "source_location": "L94", "weight": 1.0}], "raw_calls": [{"caller_nid": "tls_acmewrapper_start", "callee": "ManageSync", "is_member_call": true, "source_file": "C:\\Users\\Keanghour\\Documents\\GitHub\\FNode\\FNode\\SupportProject\\sing-box\\common\\tls\\acme.go", "source_location": "L33"}, {"caller_nid": "tls_acmewrapper_close", "callee": "Stop", "is_member_call": true, "source_file": "C:\\Users\\Keanghour\\Documents\\GitHub\\FNode\\FNode\\SupportProject\\sing-box\\common\\tls\\acme.go", "source_location": "L37"}, {"caller_nid": "tls_acmelogwriter_write", "callee": "ReplaceAll", "is_member_call": false, "source_file": "C:\\Users\\Keanghour\\Documents\\GitHub\\FNode\\FNode\\SupportProject\\sing-box\\common\\tls\\acme.go", "source_location": "L46"}, {"caller_nid": "tls_acmelogwriter_write", "callee": "string", "is_member_call": false, "source_file": "C:\\Users\\Keanghour\\Documents\\GitHub\\FNode\\FNode\\SupportProject\\sing-box\\common\\tls\\acme.go", "source_location": "L46"}, {"caller_nid": "tls_acmelogwriter_write", "callee": "HasPrefix", "is_member_call": false, "source_file": "C:\\Users\\Keanghour\\Documents\\GitHub\\FNode\\FNode\\SupportProject\\sing-box\\common\\tls\\acme.go", "source_location": "L48"}, {"caller_nid": "tls_acmelogwriter_write", "callee": "Error", "is_member_call": true, "source_file": "C:\\Users\\Keanghour\\Documents\\GitHub\\FNode\\FNode\\SupportProject\\sing-box\\common\\tls\\acme.go", "source_location": "L49"}, {"caller_nid": "tls_acmelogwriter_write", "callee": "HasPrefix", "is_member_call": false, "source_file": "C:\\Users\\Keanghour\\Documents\\GitHub\\FNode\\FNode\\SupportProject\\sing-box\\common\\tls\\acme.go", "source_location": "L50"}, {"caller_nid": "tls_acmelogwriter_write", "callee": "Warn", "is_member_call": true, "source_file": "C:\\Users\\Keanghour\\Documents\\GitHub\\FNode\\FNode\\SupportProject\\sing-box\\common\\tls\\acme.go", "source_location": "L51"}, {"caller_nid": "tls_acmelogwriter_write", "callee": "HasPrefix", "is_member_call": false, "source_file": "C:\\Users\\Keanghour\\Documents\\GitHub\\FNode\\FNode\\SupportProject\\sing-box\\common\\tls\\acme.go", "source_location": "L52"}, {"caller_nid": "tls_acmelogwriter_write", "callee": "Info", "is_member_call": true, "source_file": "C:\\Users\\Keanghour\\Documents\\GitHub\\FNode\\FNode\\SupportProject\\sing-box\\common\\tls\\acme.go", "source_location": "L53"}, {"caller_nid": "tls_acmelogwriter_write", "callee": "HasPrefix", "is_member_call": false, "source_file": "C:\\Users\\Keanghour\\Documents\\GitHub\\FNode\\FNode\\SupportProject\\sing-box\\common\\tls\\acme.go", "source_location": "L54"}, {"caller_nid": "tls_acmelogwriter_write", "callee": "Debug", "is_member_call": true, "source_file": "C:\\Users\\Keanghour\\Documents\\GitHub\\FNode\\FNode\\SupportProject\\sing-box\\common\\tls\\acme.go", "source_location": "L55"}, {"caller_nid": "tls_acmelogwriter_write", "callee": "Debug", "is_member_call": true, "source_file": "C:\\Users\\Keanghour\\Documents\\GitHub\\FNode\\FNode\\SupportProject\\sing-box\\common\\tls\\acme.go", "source_location": "L57"}, {"caller_nid": "tls_acmelogwriter_write", "callee": "len", "is_member_call": false, "source_file": "C:\\Users\\Keanghour\\Documents\\GitHub\\FNode\\FNode\\SupportProject\\sing-box\\common\\tls\\acme.go", "source_location": "L59"}, {"caller_nid": "tls_acme_encoderconfig", "callee": "NewProductionEncoderConfig", "is_member_call": false, "source_file": "C:\\Users\\Keanghour\\Documents\\GitHub\\FNode\\FNode\\SupportProject\\sing-box\\common\\tls\\acme.go", "source_location": "L67"}, {"caller_nid": "tls_acme_startacme", "callee": "HasPrefix", "is_member_call": false, "source_file": "C:\\Users\\Keanghour\\Documents\\GitHub\\FNode\\FNode\\SupportProject\\sing-box\\common\\tls\\acme.go", "source_location": "L80"}, {"caller_nid": "tls_acme_startacme", "callee": "New", "is_member_call": false, "source_file": "C:\\Users\\Keanghour\\Documents\\GitHub\\FNode\\FNode\\SupportProject\\sing-box\\common\\tls\\acme.go", "source_location": "L81"}, {"caller_nid": "tls_acme_startacme", "callee": "New", "is_member_call": false, "source_file": "C:\\Users\\Keanghour\\Documents\\GitHub\\FNode\\FNode\\SupportProject\\sing-box\\common\\tls\\acme.go", "source_location": "L93"}, {"caller_nid": "tls_acme_startacme", "callee": "NewCore", "is_member_call": false, "source_file": "C:\\Users\\Keanghour\\Documents\\GitHub\\FNode\\FNode\\SupportProject\\sing-box\\common\\tls\\acme.go", "source_location": "L93"}, {"caller_nid": "tls_acme_startacme", "callee": "NewConsoleEncoder", "is_member_call": false, "source_file": "C:\\Users\\Keanghour\\Documents\\GitHub\\FNode\\FNode\\SupportProject\\sing-box\\common\\tls\\acme.go", "source_location": "L94"}, {"caller_nid": "tls_acme_startacme", "callee": "int", "is_member_call": false, "source_file": "C:\\Users\\Keanghour\\Documents\\GitHub\\FNode\\FNode\\SupportProject\\sing-box\\common\\tls\\acme.go", "source_location": "L109"}, {"caller_nid": "tls_acme_startacme", "callee": "int", "is_member_call": false, "source_file": "C:\\Users\\Keanghour\\Documents\\GitHub\\FNode\\FNode\\SupportProject\\sing-box\\common\\tls\\acme.go", "source_location": "L110"}, {"caller_nid": "tls_acme_startacme", "callee": "New", "is_member_call": false, "source_file": "C:\\Users\\Keanghour\\Documents\\GitHub\\FNode\\FNode\\SupportProject\\sing-box\\common\\tls\\acme.go", "source_location": "L138"}, {"caller_nid": "tls_acme_startacme", "callee": "NewACMEIssuer", "is_member_call": false, "source_file": "C:\\Users\\Keanghour\\Documents\\GitHub\\FNode\\FNode\\SupportProject\\sing-box\\common\\tls\\acme.go", "source_location": "L145"}, {"caller_nid": "tls_acme_startacme", "callee": "NewCache", "is_member_call": false, "source_file": "C:\\Users\\Keanghour\\Documents\\GitHub\\FNode\\FNode\\SupportProject\\sing-box\\common\\tls\\acme.go", "source_location": "L146"}, {"caller_nid": "tls_acme_startacme", "callee": "New", "is_member_call": false, "source_file": "C:\\Users\\Keanghour\\Documents\\GitHub\\FNode\\FNode\\SupportProject\\sing-box\\common\\tls\\acme.go", "source_location": "L152"}]}