{"nodes": [{"id": "c_users_keanghour_documents_github_fnode_fnode_supportproject_sing_box_common_mux_router_go", "label": "router.go", "file_type": "code", "source_file": "C:\\Users\\Keanghour\\Documents\\GitHub\\FNode\\FNode\\SupportProject\\sing-box\\common\\mux\\router.go", "source_location": "L1"}, {"id": "mux_router", "label": "Router", "file_type": "code", "source_file": "C:\\Users\\Keanghour\\Documents\\GitHub\\FNode\\FNode\\SupportProject\\sing-box\\common\\mux\\router.go", "source_location": "L17"}, {"id": "mux_router_newrouterwithoptions", "label": "NewRouterWithOptions()", "file_type": "code", "source_file": "C:\\Users\\Keanghour\\Documents\\GitHub\\FNode\\FNode\\SupportProject\\sing-box\\common\\mux\\router.go", "source_location": "L22"}, {"id": "mux_router_routeconnection", "label": ".RouteConnection()", "file_type": "code", "source_file": "C:\\Users\\Keanghour\\Documents\\GitHub\\FNode\\FNode\\SupportProject\\sing-box\\common\\mux\\router.go", "source_location": "L56"}, {"id": "mux_router_routepacketconnection", "label": ".RoutePacketConnection()", "file_type": "code", "source_file": "C:\\Users\\Keanghour\\Documents\\GitHub\\FNode\\FNode\\SupportProject\\sing-box\\common\\mux\\router.go", "source_location": "L66"}, {"id": "mux_router_routeconnectionex", "label": ".RouteConnectionEx()", "file_type": "code", "source_file": "C:\\Users\\Keanghour\\Documents\\GitHub\\FNode\\FNode\\SupportProject\\sing-box\\common\\mux\\router.go", "source_location": "L70"}, {"id": "mux_router_routepacketconnectionex", "label": ".RoutePacketConnectionEx()", "file_type": "code", "source_file": "C:\\Users\\Keanghour\\Documents\\GitHub\\FNode\\FNode\\SupportProject\\sing-box\\common\\mux\\router.go", "source_location": "L78"}], "edges": [{"source": "c_users_keanghour_documents_github_fnode_fnode_supportproject_sing_box_common_mux_router_go", "target": "go_pkg_context", "relation": "imports_from", "confidence": "EXTRACTED", "source_file": "C:\\Users\\Keanghour\\Documents\\GitHub\\FNode\\FNode\\SupportProject\\sing-box\\common\\mux\\router.go", "source_location": "L4", "weight": 1.0, "context": "import"}, {"source": "c_users_keanghour_documents_github_fnode_fnode_supportproject_sing_box_common_mux_router_go", "target": "go_pkg_net", "relation": "imports_from", "confidence": "EXTRACTED", "source_file": "C:\\Users\\Keanghour\\Documents\\GitHub\\FNode\\FNode\\SupportProject\\sing-box\\common\\mux\\router.go", "source_location": "L5", "weight": 1.0, "context": "import"}, {"source": "c_users_keanghour_documents_github_fnode_fnode_supportproject_sing_box_common_mux_router_go", "target": "go_pkg_github_com_sagernet_sing_box_adapter", "relation": "imports_from", "confidence": "EXTRACTED", "source_file": "C:\\Users\\Keanghour\\Documents\\GitHub\\FNode\\FNode\\SupportProject\\sing-box\\common\\mux\\router.go", "source_location": "L7", "weight": 1.0, "context": "import"}, {"source": "c_users_keanghour_documents_github_fnode_fnode_supportproject_sing_box_common_mux_router_go", "target": "go_pkg_github_com_sagernet_sing_box_constant", "relation": "imports_from", "confidence": "EXTRACTED", "source_file": "C:\\Users\\Keanghour\\Documents\\GitHub\\FNode\\FNode\\SupportProject\\sing-box\\common\\mux\\router.go", "source_location": "L8", "weight": 1.0, "context": "import"}, {"source": "c_users_keanghour_documents_github_fnode_fnode_supportproject_sing_box_common_mux_router_go", "target": "go_pkg_github_com_sagernet_sing_box_log", "relation": "imports_from", "confidence": "EXTRACTED", "source_file": "C:\\Users\\Keanghour\\Documents\\GitHub\\FNode\\FNode\\SupportProject\\sing-box\\common\\mux\\router.go", "source_location": "L9", "weight": 1.0, "context": "import"}, {"source": "c_users_keanghour_documents_github_fnode_fnode_supportproject_sing_box_common_mux_router_go", "target": "go_pkg_github_com_sagernet_sing_box_option", "relation": "imports_from", "confidence": "EXTRACTED", "source_file": "C:\\Users\\Keanghour\\Documents\\GitHub\\FNode\\FNode\\SupportProject\\sing-box\\common\\mux\\router.go", "source_location": "L10", "weight": 1.0, "context": "import"}, {"source": "c_users_keanghour_documents_github_fnode_fnode_supportproject_sing_box_common_mux_router_go", "target": "go_pkg_github_com_sagernet_sing_mux", "relation": "imports_from", "confidence": "EXTRACTED", "source_file": "C:\\Users\\Keanghour\\Documents\\GitHub\\FNode\\FNode\\SupportProject\\sing-box\\common\\mux\\router.go", "source_location": "L11", "weight": 1.0, "context": "import"}, {"source": "c_users_keanghour_documents_github_fnode_fnode_supportproject_sing_box_common_mux_router_go", "target": "go_pkg_github_com_sagernet_sing_common_exceptions", "relation": "imports_from", "confidence": "EXTRACTED", "source_file": "C:\\Users\\Keanghour\\Documents\\GitHub\\FNode\\FNode\\SupportProject\\sing-box\\common\\mux\\router.go", "source_location": "L12", "weight": 1.0, "context": "import"}, {"source": "c_users_keanghour_documents_github_fnode_fnode_supportproject_sing_box_common_mux_router_go", "target": "go_pkg_github_com_sagernet_sing_common_logger", "relation": "imports_from", "confidence": "EXTRACTED", "source_file": "C:\\Users\\Keanghour\\Documents\\GitHub\\FNode\\FNode\\SupportProject\\sing-box\\common\\mux\\router.go", "source_location": "L13", "weight": 1.0, "context": "import"}, {"source": "c_users_keanghour_documents_github_fnode_fnode_supportproject_sing_box_common_mux_router_go", "target": "go_pkg_github_com_sagernet_sing_common_network", "relation": "imports_from", "confidence": "EXTRACTED", "source_file": "C:\\Users\\Keanghour\\Documents\\GitHub\\FNode\\FNode\\SupportProject\\sing-box\\common\\mux\\router.go", "source_location": "L14", "weight": 1.0, "context": "import"}, {"source": "c_users_keanghour_documents_github_fnode_fnode_supportproject_sing_box_common_mux_router_go", "target": "mux_router", "relation": "contains", "confidence": "EXTRACTED", "source_file": "C:\\Users\\Keanghour\\Documents\\GitHub\\FNode\\FNode\\SupportProject\\sing-box\\common\\mux\\router.go", "source_location": "L17", "weight": 1.0}, {"source": "c_users_keanghour_documents_github_fnode_fnode_supportproject_sing_box_common_mux_router_go", "target": "mux_router_newrouterwithoptions", "relation": "contains", "confidence": "EXTRACTED", "source_file": "C:\\Users\\Keanghour\\Documents\\GitHub\\FNode\\FNode\\SupportProject\\sing-box\\common\\mux\\router.go", "source_location": "L22", "weight": 1.0}, {"source": "mux_router", "target": "mux_router_routeconnection", "relation": "method", "confidence": "EXTRACTED", "source_file": "C:\\Users\\Keanghour\\Documents\\GitHub\\FNode\\FNode\\SupportProject\\sing-box\\common\\mux\\router.go", "source_location": "L56", "weight": 1.0}, {"source": "mux_router", "target": "mux_router_routepacketconnection", "relation": "method", "confidence": "EXTRACTED", "source_file": "C:\\Users\\Keanghour\\Documents\\GitHub\\FNode\\FNode\\SupportProject\\sing-box\\common\\mux\\router.go", "source_location": "L66", "weight": 1.0}, {"source": "mux_router", "target": "mux_router_routeconnectionex", "relation": "method", "confidence": "EXTRACTED", "source_file": "C:\\Users\\Keanghour\\Documents\\GitHub\\FNode\\FNode\\SupportProject\\sing-box\\common\\mux\\router.go", "source_location": "L70", "weight": 1.0}, {"source": "mux_router", "target": "mux_router_routepacketconnectionex", "relation": "method", "confidence": "EXTRACTED", "source_file": "C:\\Users\\Keanghour\\Documents\\GitHub\\FNode\\FNode\\SupportProject\\sing-box\\common\\mux\\router.go", "source_location": "L78", "weight": 1.0}], "raw_calls": [{"caller_nid": "mux_router_newrouterwithoptions", "callee": "uint64", "is_member_call": false, "source_file": "C:\\Users\\Keanghour\\Documents\\GitHub\\FNode\\FNode\\SupportProject\\sing-box\\common\\mux\\router.go", "source_location": "L30"}, {"caller_nid": "mux_router_newrouterwithoptions", "callee": "uint64", "is_member_call": false, "source_file": "C:\\Users\\Keanghour\\Documents\\GitHub\\FNode\\FNode\\SupportProject\\sing-box\\common\\mux\\router.go", "source_location": "L31"}, {"caller_nid": "mux_router_newrouterwithoptions", "callee": "New", "is_member_call": false, "source_file": "C:\\Users\\Keanghour\\Documents\\GitHub\\FNode\\FNode\\SupportProject\\sing-box\\common\\mux\\router.go", "source_location": "L34"}, {"caller_nid": "mux_router_newrouterwithoptions", "callee": "New", "is_member_call": false, "source_file": "C:\\Users\\Keanghour\\Documents\\GitHub\\FNode\\FNode\\SupportProject\\sing-box\\common\\mux\\router.go", "source_location": "L37"}, {"caller_nid": "mux_router_newrouterwithoptions", "callee": "NewService", "is_member_call": true, "source_file": "C:\\Users\\Keanghour\\Documents\\GitHub\\FNode\\FNode\\SupportProject\\sing-box\\common\\mux\\router.go", "source_location": "L40"}, {"caller_nid": "mux_router_newrouterwithoptions", "callee": "ContextWithNewID", "is_member_call": false, "source_file": "C:\\Users\\Keanghour\\Documents\\GitHub\\FNode\\FNode\\SupportProject\\sing-box\\common\\mux\\router.go", "source_location": "L42"}, {"caller_nid": "mux_router_newrouterwithoptions", "callee": "NewRouteContextHandlerEx", "is_member_call": false, "source_file": "C:\\Users\\Keanghour\\Documents\\GitHub\\FNode\\FNode\\SupportProject\\sing-box\\common\\mux\\router.go", "source_location": "L45"}, {"caller_nid": "mux_router_routeconnection", "callee": "NewConnection", "is_member_call": true, "source_file": "C:\\Users\\Keanghour\\Documents\\GitHub\\FNode\\FNode\\SupportProject\\sing-box\\common\\mux\\router.go", "source_location": "L59"}, {"caller_nid": "mux_router_routeconnection", "callee": "WithContext", "is_member_call": false, "source_file": "C:\\Users\\Keanghour\\Documents\\GitHub\\FNode\\FNode\\SupportProject\\sing-box\\common\\mux\\router.go", "source_location": "L59"}, {"caller_nid": "mux_router_routeconnection", "callee": "UpstreamMetadata", "is_member_call": false, "source_file": "C:\\Users\\Keanghour\\Documents\\GitHub\\FNode\\FNode\\SupportProject\\sing-box\\common\\mux\\router.go", "source_location": "L59"}, {"caller_nid": "mux_router_routeconnection", "callee": "RouteConnection", "is_member_call": true, "source_file": "C:\\Users\\Keanghour\\Documents\\GitHub\\FNode\\FNode\\SupportProject\\sing-box\\common\\mux\\router.go", "source_location": "L61"}, {"caller_nid": "mux_router_routepacketconnection", "callee": "RoutePacketConnection", "is_member_call": true, "source_file": "C:\\Users\\Keanghour\\Documents\\GitHub\\FNode\\FNode\\SupportProject\\sing-box\\common\\mux\\router.go", "source_location": "L67"}, {"caller_nid": "mux_router_routeconnectionex", "callee": "NewConnectionEx", "is_member_call": true, "source_file": "C:\\Users\\Keanghour\\Documents\\GitHub\\FNode\\FNode\\SupportProject\\sing-box\\common\\mux\\router.go", "source_location": "L72"}, {"caller_nid": "mux_router_routeconnectionex", "callee": "WithContext", "is_member_call": false, "source_file": "C:\\Users\\Keanghour\\Documents\\GitHub\\FNode\\FNode\\SupportProject\\sing-box\\common\\mux\\router.go", "source_location": "L72"}, {"caller_nid": "mux_router_routeconnectionex", "callee": "RouteConnectionEx", "is_member_call": true, "source_file": "C:\\Users\\Keanghour\\Documents\\GitHub\\FNode\\FNode\\SupportProject\\sing-box\\common\\mux\\router.go", "source_location": "L75"}, {"caller_nid": "mux_router_routepacketconnectionex", "callee": "RoutePacketConnectionEx", "is_member_call": true, "source_file": "C:\\Users\\Keanghour\\Documents\\GitHub\\FNode\\FNode\\SupportProject\\sing-box\\common\\mux\\router.go", "source_location": "L79"}]}