{"nodes": [{"id": "c_users_keanghour_documents_github_fnode_fnode_supportproject_sing_box_common_sniff_rdp_go", "label": "rdp.go", "file_type": "code", "source_file": "C:\\Users\\Keanghour\\Documents\\GitHub\\FNode\\FNode\\SupportProject\\sing-box\\common\\sniff\\rdp.go", "source_location": "L1"}, {"id": "sniff_rdp_rdp", "label": "RDP()", "file_type": "code", "source_file": "C:\\Users\\Keanghour\\Documents\\GitHub\\FNode\\FNode\\SupportProject\\sing-box\\common\\sniff\\rdp.go", "source_location": "L15"}], "edges": [{"source": "c_users_keanghour_documents_github_fnode_fnode_supportproject_sing_box_common_sniff_rdp_go", "target": "go_pkg_context", "relation": "imports_from", "confidence": "EXTRACTED", "source_file": "C:\\Users\\Keanghour\\Documents\\GitHub\\FNode\\FNode\\SupportProject\\sing-box\\common\\sniff\\rdp.go", "source_location": "L4", "weight": 1.0, "context": "import"}, {"source": "c_users_keanghour_documents_github_fnode_fnode_supportproject_sing_box_common_sniff_rdp_go", "target": "go_pkg_encoding_binary", "relation": "imports_from", "confidence": "EXTRACTED", "source_file": "C:\\Users\\Keanghour\\Documents\\GitHub\\FNode\\FNode\\SupportProject\\sing-box\\common\\sniff\\rdp.go", "source_location": "L5", "weight": 1.0, "context": "import"}, {"source": "c_users_keanghour_documents_github_fnode_fnode_supportproject_sing_box_common_sniff_rdp_go", "target": "go_pkg_io", "relation": "imports_from", "confidence": "EXTRACTED", "source_file": "C:\\Users\\Keanghour\\Documents\\GitHub\\FNode\\FNode\\SupportProject\\sing-box\\common\\sniff\\rdp.go", "source_location": "L6", "weight": 1.0, "context": "import"}, {"source": "c_users_keanghour_documents_github_fnode_fnode_supportproject_sing_box_common_sniff_rdp_go", "target": "go_pkg_os", "relation": "imports_from", "confidence": "EXTRACTED", "source_file": "C:\\Users\\Keanghour\\Documents\\GitHub\\FNode\\FNode\\SupportProject\\sing-box\\common\\sniff\\rdp.go", "source_location": "L7", "weight": 1.0, "context": "import"}, {"source": "c_users_keanghour_documents_github_fnode_fnode_supportproject_sing_box_common_sniff_rdp_go", "target": "go_pkg_github_com_sagernet_sing_box_adapter", "relation": "imports_from", "confidence": "EXTRACTED", "source_file": "C:\\Users\\Keanghour\\Documents\\GitHub\\FNode\\FNode\\SupportProject\\sing-box\\common\\sniff\\rdp.go", "source_location": "L9", "weight": 1.0, "context": "import"}, {"source": "c_users_keanghour_documents_github_fnode_fnode_supportproject_sing_box_common_sniff_rdp_go", "target": "go_pkg_github_com_sagernet_sing_box_constant", "relation": "imports_from", "confidence": "EXTRACTED", "source_file": "C:\\Users\\Keanghour\\Documents\\GitHub\\FNode\\FNode\\SupportProject\\sing-box\\common\\sniff\\rdp.go", "source_location": "L10", "weight": 1.0, "context": "import"}, {"source": "c_users_keanghour_documents_github_fnode_fnode_supportproject_sing_box_common_sniff_rdp_go", "target": "go_pkg_github_com_sagernet_sing_common_exceptions", "relation": "imports_from", "confidence": "EXTRACTED", "source_file": "C:\\Users\\Keanghour\\Documents\\GitHub\\FNode\\FNode\\SupportProject\\sing-box\\common\\sniff\\rdp.go", "source_location": "L11", "weight": 1.0, "context": "import"}, {"source": "c_users_keanghour_documents_github_fnode_fnode_supportproject_sing_box_common_sniff_rdp_go", "target": "go_pkg_github_com_sagernet_sing_common_rw", "relation": "imports_from", "confidence": "EXTRACTED", "source_file": "C:\\Users\\Keanghour\\Documents\\GitHub\\FNode\\FNode\\SupportProject\\sing-box\\common\\sniff\\rdp.go", "source_location": "L12", "weight": 1.0, "context": "import"}, {"source": "c_users_keanghour_documents_github_fnode_fnode_supportproject_sing_box_common_sniff_rdp_go", "target": "sniff_rdp_rdp", "relation": "contains", "confidence": "EXTRACTED", "source_file": "C:\\Users\\Keanghour\\Documents\\GitHub\\FNode\\FNode\\SupportProject\\sing-box\\common\\sniff\\rdp.go", "source_location": "L15", "weight": 1.0}], "raw_calls": [{"caller_nid": "sniff_rdp_rdp", "callee": "Read", "is_member_call": false, "source_file": "C:\\Users\\Keanghour\\Documents\\GitHub\\FNode\\FNode\\SupportProject\\sing-box\\common\\sniff\\rdp.go", "source_location": "L17"}, {"caller_nid": "sniff_rdp_rdp", "callee": "Cause1", "is_member_call": false, "source_file": "C:\\Users\\Keanghour\\Documents\\GitHub\\FNode\\FNode\\SupportProject\\sing-box\\common\\sniff\\rdp.go", "source_location": "L19"}, {"caller_nid": "sniff_rdp_rdp", "callee": "Read", "is_member_call": false, "source_file": "C:\\Users\\Keanghour\\Documents\\GitHub\\FNode\\FNode\\SupportProject\\sing-box\\common\\sniff\\rdp.go", "source_location": "L26"}, {"caller_nid": "sniff_rdp_rdp", "callee": "Cause1", "is_member_call": false, "source_file": "C:\\Users\\Keanghour\\Documents\\GitHub\\FNode\\FNode\\SupportProject\\sing-box\\common\\sniff\\rdp.go", "source_location": "L28"}, {"caller_nid": "sniff_rdp_rdp", "callee": "Read", "is_member_call": false, "source_file": "C:\\Users\\Keanghour\\Documents\\GitHub\\FNode\\FNode\\SupportProject\\sing-box\\common\\sniff\\rdp.go", "source_location": "L35"}, {"caller_nid": "sniff_rdp_rdp", "callee": "Cause1", "is_member_call": false, "source_file": "C:\\Users\\Keanghour\\Documents\\GitHub\\FNode\\FNode\\SupportProject\\sing-box\\common\\sniff\\rdp.go", "source_location": "L37"}, {"caller_nid": "sniff_rdp_rdp", "callee": "Read", "is_member_call": false, "source_file": "C:\\Users\\Keanghour\\Documents\\GitHub\\FNode\\FNode\\SupportProject\\sing-box\\common\\sniff\\rdp.go", "source_location": "L45"}, {"caller_nid": "sniff_rdp_rdp", "callee": "Cause1", "is_member_call": false, "source_file": "C:\\Users\\Keanghour\\Documents\\GitHub\\FNode\\FNode\\SupportProject\\sing-box\\common\\sniff\\rdp.go", "source_location": "L47"}, {"caller_nid": "sniff_rdp_rdp", "callee": "Read", "is_member_call": false, "source_file": "C:\\Users\\Keanghour\\Documents\\GitHub\\FNode\\FNode\\SupportProject\\sing-box\\common\\sniff\\rdp.go", "source_location": "L55"}, {"caller_nid": "sniff_rdp_rdp", "callee": "Cause1", "is_member_call": false, "source_file": "C:\\Users\\Keanghour\\Documents\\GitHub\\FNode\\FNode\\SupportProject\\sing-box\\common\\sniff\\rdp.go", "source_location": "L57"}, {"caller_nid": "sniff_rdp_rdp", "callee": "SkipN", "is_member_call": false, "source_file": "C:\\Users\\Keanghour\\Documents\\GitHub\\FNode\\FNode\\SupportProject\\sing-box\\common\\sniff\\rdp.go", "source_location": "L63"}, {"caller_nid": "sniff_rdp_rdp", "callee": "Cause1", "is_member_call": false, "source_file": "C:\\Users\\Keanghour\\Documents\\GitHub\\FNode\\FNode\\SupportProject\\sing-box\\common\\sniff\\rdp.go", "source_location": "L65"}, {"caller_nid": "sniff_rdp_rdp", "callee": "Read", "is_member_call": false, "source_file": "C:\\Users\\Keanghour\\Documents\\GitHub\\FNode\\FNode\\SupportProject\\sing-box\\common\\sniff\\rdp.go", "source_location": "L69"}, {"caller_nid": "sniff_rdp_rdp", "callee": "Cause1", "is_member_call": false, "source_file": "C:\\Users\\Keanghour\\Documents\\GitHub\\FNode\\FNode\\SupportProject\\sing-box\\common\\sniff\\rdp.go", "source_location": "L71"}, {"caller_nid": "sniff_rdp_rdp", "callee": "Read", "is_member_call": false, "source_file": "C:\\Users\\Keanghour\\Documents\\GitHub\\FNode\\FNode\\SupportProject\\sing-box\\common\\sniff\\rdp.go", "source_location": "L77"}, {"caller_nid": "sniff_rdp_rdp", "callee": "Cause1", "is_member_call": false, "source_file": "C:\\Users\\Keanghour\\Documents\\GitHub\\FNode\\FNode\\SupportProject\\sing-box\\common\\sniff\\rdp.go", "source_location": "L79"}, {"caller_nid": "sniff_rdp_rdp", "callee": "Read", "is_member_call": false, "source_file": "C:\\Users\\Keanghour\\Documents\\GitHub\\FNode\\FNode\\SupportProject\\sing-box\\common\\sniff\\rdp.go", "source_location": "L82"}, {"caller_nid": "sniff_rdp_rdp", "callee": "Cause1", "is_member_call": false, "source_file": "C:\\Users\\Keanghour\\Documents\\GitHub\\FNode\\FNode\\SupportProject\\sing-box\\common\\sniff\\rdp.go", "source_location": "L84"}]}